{"model": {"base_value": 667.5896, "learning_rate": 0.1, "trees": [{"nodes": [{"f": 0, "t": 0.5, "l": 1, "r": 8, "v": -4.263256414560601e-14}, {"f": 8, "t": 668.1607055664062, "l": 2, "r": 5, "v": -311.4227818181818}, {"f": 2, "t": 49.0, "l": 3, "r": 4, "v": -344.381475}, {"f": -2, "t": null, "l": -1, "r": -1, "v": -361.75360000000006}, {"f": -2, "t": null, "l": -1, "r": -1, "v": -83.79960000000005}, {"f": 2, "t": 11.5, "l": 6, "r": 7, "v": -223.53293333333332}, {"f": -2, "t": null, "l": -1, "r": -1, "v": 29.81039999999996}, {"f": -2, "t": null, "l": -1, "r": -1, "v": -274.2016}, {"f": 8, "t": 747.394287109375, "l": 9, "r": 12, "v": 87.83719487179486}, {"f": 8, "t": 644.1792907714844, "l": 10, "r": 11, "v": 3.456733333333314}, {"f": -2, "t": null, "l": -1, "r": -1, "v": -43.563647619047636}, {"f": -2, "t": null, "l": -1, "r": -1, "v": 113.17095555555551}, {"f": 8, "t": 966.8307189941406, "l": 13, "r": 14, "v": 369.1054}, {"f": -2, "t": null, "l": -1, "r": -1, "v": 463.8913090909091}, {"f": -2, "t": null, "l": -1, "r": -1, "v": 220.15611428571427}]}, {"nodes": [{"f": 0, "t": 0.5, "l": 1, "r": 8, "v": -2.1032064978498965e-14}, {"f": 1, "t": 15.0, "l": 2, "r": 5, "v": -280.28050363636373}, {"f": 6, "t": 772.4550170898438, "l": 3, "r": 4, "v": -340.54984}, {"f": -2, "t": null, "l": -1, "r": -1, "v": -379.77344}, {"f": -2, "t": null, "l": -1, "r": -1, "v": -262.10264000000006}, {"f": 8, "t": 671.8935852050781, "l": 6, "r": 7, "v": -238.5555784615385}, {"f": -2, "t": null, "l": -1, "r": -1, "v": -275.123728888889}, {"f": -2, "t": null, "l": -1, "r": -1, "v": -156.27724}, {"f": 9, "t": 714.6965942382812, "l": 9, "r": 12, "v": 79.05347538461533}, {"f": 5, "t": 204.5, "l": 10, "r": 11, "v": 8.126711906158326}, {"f": -2, "t": null, "l": -1, "r": -1, "v": -54.17735288515411}, {"f": -2, "t": null, "l": -1, "r": -1, "v": 83.78164772418056}, {"f": 5, "t": 312.5, "l": 13, "r": 14, "v": 353.8946838636364}, {"f": -2, "t": null, "l": -1, "r": -1, "v": 814.4612690909091}, {"f": -2, "t": null, "l": -1, "r": -1, "v": 288.0994574025973}]}, {"nodes": [{"f": 0, "t": 0.5, "l": 1, "r": 8, "v": -5.400124791776761e-14}, {"f": 1, "t": 15.0, "l": 2, "r": 5, "v": -252.2524532727273}, {"f": 6, "t": 772.4550170898438, "l": 3, "r": 4, "v": -306.494856}, {"f": -2, "t": null, "l": -1, "r": -1, "v": -341.79609600000003}, {"f": -2, "t": null, "l": -1, "r": -1, "v": -235.892376}, {"f": 8, "t": 671.8935852050781, "l": 6, "r": 7, "v": -214.70002061538466}, {"f": -2, "t": null, "l": -1, "r": -1, "v": -247.61135600000003}, {"f": -2, "t": null, "l": -1, "r": -1, "v": -140.64951599999995}, {"f": 9, "t": 714.6965942382812, "l": 9, "r": 12, "v": 71.14812784615386}, {"f": 8, "t": 644.1792907714844, "l": 10, "r": 11, "v": 7.314040715542481}, {"f": -2, "t": null, "l": -1, "r": -1, "v": -36.41733805642438}, {"f": -2, "t": null, "l": -1, "r": -1, "v": 99.14993613667289}, {"f": 2, "t": 20.5, "l": 13, "r": 14, "v": 318.5052154772727}, {"f": -2, "t": null, "l": -1, "r": -1, "v": 733.0151421818182}, {"f": -2, "t": null, "l": -1, "r": -1, "v": 259.2895116623376}]}, {"nodes": [{"f": 0, "t": 0.5, "l": 1, "r": 6, "v": -6.195932655828074e-14}, {"f": 2, "t": 49.0, "l": 2, "r": 5, "v": -227.02720794545456}, {"f": 8, "t": 631.0228576660156, "l": 3, "r": 4, "v": -236.73583063280427}, {"f": -2, "t": null, "l": -1, "r": -1, "v": -282.5946200969697}, {"f": -2, "t": null, "l": -1, "r": -1, "v": -186.2911622222222}, {"f": -2, "t": null, "l": -1, "r": -1, "v": -23.146131511111207}, {"f": 9, "t": 714.6965942382812, "l": 7, "r": 10, "v": 64.03331506153839}, {"f": 5, "t": 228.5, "l": 8, "r": 9, "v": 6.5826366439881925}, {"f": -2, "t": null, "l": -1, "r": -1, "v": -35.76940115307753}, {"f": -2, "t": null, "l": -1, "r": -1, "v": 83.58634172956225}, {"f": 9, "t": 737.501953125, "l": 11, "r": 12, "v": 286.6546939295454}, {"f": -2, "t": null, "l": -1, "r": -1, "v": 659.7136279636363}, {"f": -2, "t": null, "l": -1, "r": -1, "v": 233.36056049610383}]}, {"nodes": [{"f": 0, "t": 0.5, "l": 1, "r": 6, "v": -8.810729923425243e-14}, {"f": 3, "t": 11.5, "l": 2, "r": 5, "v": -204.3244871509091}, {"f": 8, "t": 668.1607055664062, "l": 3, "r": 4, "v": -213.06224756952378}, {"f": -2, "t": null, "l": -1, "r": -1, "v": -241.31541425955552}, {"f": -2, "t": null, "l": -1, "r": -1, "v": -142.42933084444442}, {"f": -2, "t": null, "l": -1, "r": -1, "v": -20.831518360000132}, {"f": 8, "t": 747.394287109375, "l": 7, "r": 10, "v": 57.62998355538452}, {"f": 9, "t": 617.1321716308594, "l": 8, "r": 9, "v": 1.7237028611800553}, {"f": -2, "t": null, "l": -1, "r": -1, "v": -28.76979737963953}, {"f": -2, "t": null, "l": -1, "r": -1, "v": 93.20420358363884}, {"f": 7, "t": 772.4550170898438, "l": 11, "r": 12, "v": 243.98425253606598}, {"f": -2, "t": null, "l": -1, "r": -1, "v": 333.1708778251607}, {"f": -2, "t": null, "l": -1, "r": -1, "v": 132.50097092469764}]}, {"nodes": [{"f": 0, "t": 0.5, "l": 1, "r": 8, "v": -4.376943252282217e-14}, {"f": 1, "t": 15.0, "l": 2, "r": 5, "v": -183.8920384358182}, {"f": 6, "t": 772.4550170898438, "l": 3, "r": 4, "v": -229.93198916800532}, {"f": -2, "t": null, "l": -1, "r": -1, "v": -258.47864198584506}, {"f": -2, "t": null, "l": -1, "r": -1, "v": -172.83868353232583}, {"f": 8, "t": 671.8935852050781, "l": 6, "r": 7, "v": -152.01822639045787}, {"f": -2, "t": null, "l": -1, "r": -1, "v": -177.9318758558465}, {"f": -2, "t": null, "l": -1, "r": -1, "v": -93.71251509333332}, {"f": 9, "t": 714.6965942382812, "l": 9, "r": 12, "v": 51.86698519984608}, {"f": 2, "t": 47.5, "l": 10, "r": 11, "v": 5.006479398265722}, {"f": -2, "t": null, "l": -1, "r": -1, "v": 20.21738516045269}, {"f": -2, "t": null, "l": -1, "r": -1, "v": -168.39784629066583}, {"f": 9, "t": 737.501953125, "l": 13, "r": 14, "v": 233.45144518097}, {"f": -2, "t": null, "l": -1, "r": -1, "v": 560.4251773847566}, {"f": -2, "t": null, "l": -1, "r": -1, "v": 186.74091200900043}]}, {"nodes": [{"f": 0, "t": 0.5, "l": 1, "r": 6, "v": -7.560174708487466e-14}, {"f": 2, "t": 49.0, "l": 2, "r": 5, "v": -165.50283459223635}, {"f": 6, "t": 651.8450012207031, "l": 3, "r": 4, "v": -173.3384372424183}, {"f": -2, "t": null, "l": -1, "r": -1, "v": -228.46332807609625}, {"f": -2, "t": null, "l": -1, "r": -1, "v": -145.77599182557935}, {"f": -2, "t": null, "l": -1, "r": -1, "v": -0.9551789384155427}, {"f": 8, "t": 747.394287109375, "l": 7, "r": 10, "v": 46.68028667986149}, {"f": 9, "t": 617.1321716308594, "l": 8, "r": 9, "v": 1.1013876544427983}, {"f": -2, "t": null, "l": -1, "r": -1, "v": -25.81883136381949}, {"f": -2, "t": null, "l": -1, "r": -1, "v": 81.86204470922966}, {"f": 1, "t": 7.0, "l": 11, "r": 12, "v": 198.60995009792362}, {"f": -2, "t": null, "l": -1, "r": -1, "v": -15.97569589507369}, {"f": -2, "t": null, "l": -1, "r": -1, "v": 241.52707929652306}]}, {"nodes": [{"f": 0, "t": 0.5, "l": 1, "r": 8, "v": -3.012701199622825e-14}, {"f": 1, "t": 15.0, "l": 2, "r": 5, "v": -148.95255113301275}, {"f": 6, "t": 772.4550170898438, "l": 3, "r": 4, "v": -188.68619834640165}, {"f": -2, "t": null, "l": -1, "r": -1, "v": -212.5406895213348}, {"f": -2, "t": null, "l": -1, "r": -1, "v": -140.9772159965353}, {"f": 2, "t": 11.0, "l": 6, "r": 7, "v": -121.44464152374341}, {"f": -2, "t": null, "l": -1, "r": -1, "v": -30.508636041853208}, {"f": -2, "t": null, "l": -1, "r": -1, "v": -137.97846070226896}, {"f": 9, "t": 714.6965942382812, "l": 9, "r": 12, "v": 42.01225801187535}, {"f": 2, "t": 47.5, "l": 10, "r": 11, "v": 3.6201259457623713}, {"f": -2, "t": null, "l": -1, "r": -1, "v": 17.00576668883076}, {"f": -2, "t": null, "l": -1, "r": -1, "v": -148.97617852521728}, {"f": 8, "t": 966.8307189941406, "l": 13, "r": 14, "v": 190.78176976806313}, {"f": -2, "t": null, "l": -1, "r": -1, "v": 293.226492788208}, {"f": -2, "t": null, "l": -1, "r": -1, "v": 59.06712588501965}]}, {"nodes": [{"f": 0, "t": 0.5, "l": 1, "r": 6, "v": -1.5347723092418165e-14}, {"f": 3, "t": 11.5, "l": 2, "r": 5, "v": -134.05729601971146}, {"f": 8, "t": 668.1607055664062, "l": 3, "r": 4, "v": -141.05708083139544}, {"f": -2, "t": null, "l": -1, "r": -1, "v": -162.7305891300304}, {"f": -2, "t": null, "l": -1, "r": -1, "v": -86.8733100848081}, {"f": -2, "t": null, "l": -1, "r": -1, "v": 12.938185025652956}, {"f": 5, "t": 256.5, "l": 7, "r": 10, "v": 37.81103221068781}, {"f": 2, "t": 47.5, "l": 8, "r": 9, "v": -18.672892037613064}, {"f": -2, "t": null, "l": -1, "r": -1, "v": -4.93412196200801}, {"f": -2, "t": null, "l": -1, "r": -1, "v": -134.07856067269552}, {"f": 0, "t": 2.5, "l": 11, "r": 12, "v": 123.44794961940208}, {"f": -2, "t": null, "l": -1, "r": -1, "v": 70.90196445734912}, {"f": -2, "t": null, "l": -1, "r": -1, "v": 233.79451845971326}]}, {"nodes": [{"f": 0, "t": 0.5, "l": 1, "r": 6, "v": -1.5347723092418165e-14}, {"f": 3, "t": 11.5, "l": 2, "r": 5, "v": -120.65156641774028}, {"f": 6, "t": 651.8450012207031, "l": 3, "r": 4, "v": -126.95137274825588}, {"f": -2, "t": null, "l": -1, "r": -1, "v": -172.8206747050302}, {"f": -2, "t": null, "l": -1, "r": -1, "v": -104.01672176986874}, {"f": -2, "t": null, "l": -1, "r": -1, "v": 11.644366523087683}, {"f": 8, "t": 747.394287109375, "l": 7, "r": 10, "v": 34.029928989619016}, {"f": 2, "t": 47.5, "l": 8, "r": 9, "v": -1.0098691614812187}, {"f": -2, "t": null, "l": -1, "r": -1, "v": 9.86838860615012}, {"f": -2, "t": null, "l": -1, "r": -1, "v": -120.67070460542595}, {"f": 8, "t": 966.8307189941406, "l": 11, "r": 12, "v": 150.82925615995316}, {"f": -2, "t": null, "l": -1, "r": -1, "v": 220.45578215674098}, {"f": -2, "t": null, "l": -1, "r": -1, "v": 41.41614387928668}]}, {"nodes": [{"f": 0, "t": 0.5, "l": 1, "r": 8, "v": -9.663381206337363e-15}, {"f": 1, "t": 15.0, "l": 2, "r": 5, "v": -108.58640977596627}, {"f": 6, "t": 772.4550170898438, "l": 3, "r": 4, "v": -141.77061127010265}, {"f": -2, "t": null, "l": -1, "r": -1, "v": -161.28924726762102}, {"f": -2, "t": null, "l": -1, "r": -1, "v": -102.73333927506593}, {"f": 2, "t": 11.0, "l": 6, "r": 7, "v": -85.61273181848719}, {"f": -2, "t": null, "l": -1, "r": -1, "v": -1.135707653181015}, {"f": -2, "t": null, "l": -1, "r": -1, "v": -100.97219075763377}, {"f": 9, "t": 617.7377014160156, "l": 9, "r": 12, "v": 30.626936090657143}, {"f": 6, "t": 676.364990234375, "l": 10, "r": 11, "v": -17.299844505197186}, {"f": -2, "t": null, "l": -1, "r": -1, "v": -34.95750783775162}, {"f": -2, "t": null, "l": -1, "r": -1, "v": 57.25473401003272}, {"f": 0, "t": 2.5, "l": 13, "r": 14, "v": 103.29011957469436}, {"f": -2, "t": null, "l": -1, "r": -1, "v": 56.05700944781239}, {"f": -2, "t": null, "l": -1, "r": -1, "v": 202.47965084114648}]}, {"nodes": [{"f": 0, "t": 0.5, "l": 1, "r": 6, "v": 1.0800249583553523e-14}, {"f": 3, "t": 11.5, "l": 2, "r": 5, "v": -97.72776879836961}, {"f": 8, "t": 679.5471496582031, "l": 3, "r": 4, "v": -103.36133631003213}, {"f": -2, "t": null, "l": -1, "r": -1, "v": -119.29475441290145}, {"f": -2, "t": null, "l": -1, "r": -1, "v": -52.374398380850195}, {"f": -2, "t": null, "l": -1, "r": -1, "v": 20.577148946542366}, {"f": 9, "t": 763.1742858886719, "l": 7, "r": 10, "v": 27.56424248159144}, {"f": 2, "t": 21.5, "l": 8, "r": 9, "v": 8.884150531627741}, {"f": -2, "t": null, "l": -1, "r": -1, "v": 43.33180655560843}, {"f": -2, "t": null, "l": -1, "r": -1, "v": -32.022440996849326}, {"f": 7, "t": 1181.2849731445312, "l": 11, "r": 12, "v": 191.0150470437739}, {"f": -2, "t": null, "l": -1, "r": -1, "v": 267.93544479672005}, {"f": -2, "t": null, "l": -1, "r": -1, "v": -39.746146215064584}]}, {"nodes": [{"f": 8, "t": 665.8571472167969, "l": 1, "r": 8, "v": 6.252776074688882e-15}, {"f": 0, "t": 0.5, "l": 2, "r": 5, "v": -39.1103096613246}, {"f": 3, "t": 11.5, "l": 3, "r": 4, "v": -101.45175888064176}, {"f": -2, "t": null, "l": -1, "r": -1, "v": -109.44983840947707}, {"f": -2, "t": null, "l": -1, "r": -1, "v": 18.519434051888084}, {"f": 1, "t": 23.5, "l": 6, "r": 7, "v": -15.913491347160068}, {"f": -2, "t": null, "l": -1, "r": -1, "v": 1.006693229578957}, {"f": -2, "t": null, "l": -1, "r": -1, "v": -79.83418863706306}, {"f": 1, "t": 7.0, "l": 9, "r": 12, "v": 56.28068951263785}, {"f": 7, "t": 431.44500732421875, "l": 10, "r": 11, "v": -61.48103937008121}, {"f": -2, "t": null, "l": -1, "r": -1, "v": 77.805135424926}, {"f": -2, "t": null, "l": -1, "r": -1, "v": -81.37906434079653}, {"f": 9, "t": 834.8076782226562, "l": 13, "r": 14, "v": 84.82898742360004}, {"f": -2, "t": null, "l": -1, "r": -1, "v": 63.77607013276241}, {"f": -2, "t": null, "l": -1, "r": -1, "v": 411.1492054315836}]}, {"nodes": [{"f": 0, "t": 0.5, "l": 1, "r": 8, "v": 1.5347723092418165e-14}, {"f": 2, "t": 16.5, "l": 2, "r": 5, "v": -81.65623348322698}, {"f": 8, "t": 685.1007385253906, "l": 3, "r": 4, "v": -51.63248165866374}, {"f": -2, "t": null, "l": -1, "r": -1, "v": -78.2165798925211}, {"f": -2, "t": null, "l": -1, "r": -1, "v": 134.45620597833772}, {"f": 9, "t": 548.7383117675781, "l": 6, "r": 7, "v": -98.81266309726308}, {"f": -2, "t": null, "l": -1, "r": -1, "v": -46.34685945050667}, {"f": -2, "t": null, "l": -1, "r": -1, "v": -119.79898455596567}, {"f": 8, "t": 773.2478637695312, "l": 9, "r": 12, "v": 23.03124534142302}, {"f": 2, "t": 47.5, "l": 10, "r": 11, "v": 0.4918750836074244}, {"f": -2, "t": null, "l": -1, "r": -1, "v": 9.060416882783576}, {"f": -2, "t": null, "l": -1, "r": -1, "v": -100.61691814667117}, {"f": 8, "t": 966.8307189941406, "l": 13, "r": 14, "v": 126.06836652000861}, {"f": -2, "t": null, "l": -1, "r": -1, "v": 238.0095031445524}, {"f": -2, "t": null, "l": -1, "r": -1, "v": 14.127229895464827}]}, {"nodes": [{"f": 8, "t": 645.1964416503906, "l": 1, "r": 8, "v": 1.0231815394945442e-14}, {"f": 0, "t": 0.5, "l": 2, "r": 5, "v": -34.74743476226481}, {"f": 3, "t": 11.5, "l": 3, "r": 4, "v": -84.93094017980243}, {"f": -2, "t": null, "l": -1, "r": -1, "v": -93.1027183929988}, {"f": -2, "t": null, "l": -1, "r": -1, "v": 21.302176591750026}, {"f": 1, "t": 23.5, "l": 6, "r": 7, "v": -18.019599623085604}, {"f": -2, "t": null, "l": -1, "r": -1, "v": -3.7559802430536484}, {"f": -2, "t": null, "l": -1, "r": -1, "v": -70.31953734986944}, {"f": 1, "t": 7.5, "l": 9, "r": 12, "v": 44.224007879246145}, {"f": 7, "t": 431.44500732421875, "l": 10, "r": 11, "v": -58.728686231308124}, {"f": -2, "t": null, "l": -1, "r": -1, "v": 69.11858019415502}, {"f": -2, "t": null, "l": -1, "r": -1, "v": -74.70959453449102}, {"f": 9, "t": 834.8076782226562, "l": 13, "r": 14, "v": 70.69755779338868}, {"f": -2, "t": null, "l": -1, "r": -1, "v": 53.31998867562893}, {"f": -2, "t": null, "l": -1, "r": -1, "v": 357.4274482364243}]}, {"nodes": [{"f": 0, "t": 0.5, "l": 1, "r": 8, "v": 3.2969182939268646e-14}, {"f": 5, "t": 293.0, "l": 2, "r": 5, "v": -68.86091731884768}, {"f": 8, "t": 685.1007385253906, "l": 3, "r": 4, "v": -56.82996175801553}, {"f": -2, "t": null, "l": -1, "r": -1, "v": -67.6117460249503}, {"f": -2, "t": null, "l": -1, "r": -1, "v": 115.67858651294102}, {"f": 7, "t": 906.8799743652344, "l": 6, "r": 7, "v": -109.76616622567701}, {"f": -2, "t": null, "l": -1, "r": -1, "v": -75.82659482886731}, {"f": -2, "t": null, "l": -1, "r": -1, "v": -118.25105907487944}, {"f": 9, "t": 714.6965942382812, "l": 9, "r": 12, "v": 19.422310013008374}, {"f": 2, "t": 47.5, "l": 10, "r": 11, "v": -1.1008135510354349}, {"f": -2, "t": null, "l": -1, "r": -1, "v": 6.479561227244439}, {"f": -2, "t": null, "l": -1, "r": -1, "v": -87.517086023426}, {"f": 9, "t": 737.501953125, "l": 13, "r": 14, "v": 98.9494138236781}, {"f": -2, "t": null, "l": -1, "r": -1, "v": 360.8563302109774}, {"f": -2, "t": null, "l": -1, "r": -1, "v": 61.53414005406391}]}, {"nodes": [{"f": 0, "t": 0.5, "l": 1, "r": 8, "v": 5.2864379540551457e-14}, {"f": 5, "t": 293.0, "l": 2, "r": 5, "v": -61.97482558696293}, {"f": 8, "t": 685.1007385253906, "l": 3, "r": 4, "v": -51.14696558221399}, {"f": -2, "t": null, "l": -1, "r": -1, "v": -60.850571422455296}, {"f": -2, "t": null, "l": -1, "r": -1, "v": 104.11072786164698}, {"f": 7, "t": 906.8799743652344, "l": 6, "r": 7, "v": -98.7895496031093}, {"f": -2, "t": null, "l": -1, "r": -1, "v": -68.24393534598056}, {"f": -2, "t": null, "l": -1, "r": -1, "v": -106.42595316739147}, {"f": 5, "t": 333.0, "l": 9, "r": 12, "v": 17.480079011707566}, {"f": 2, "t": 20.5, "l": 10, "r": 11, "v": 4.776680605803953}, {"f": -2, "t": null, "l": -1, "r": -1, "v": 31.972769369750143}, {"f": -2, "t": null, "l": -1, "r": -1, "v": -22.41940815814224}, {"f": 6, "t": 393.72499084472656, "l": 13, "r": 14, "v": 128.6348150633642}, {"f": -2, "t": null, "l": -1, "r": -1, "v": -66.70794179750169}, {"f": -2, "t": null, "l": -1, "r": -1, "v": 193.74906735031948}]}, {"nodes": [{"f": 8, "t": 747.394287109375, "l": 1, "r": 8, "v": 8.242295734817162e-14}, {"f": 6, "t": 736.2349853515625, "l": 2, "r": 5, "v": -15.349436361131922}, {"f": 8, "t": 643.6478576660156, "l": 3, "r": 4, "v": -1.8634275729381253}, {"f": -2, "t": null, "l": -1, "r": -1, "v": -25.301289510198803}, {"f": -2, "t": null, "l": -1, "r": -1, "v": 82.8734578925428}, {"f": 8, "t": 710.1778564453125, "l": 6, "r": 7, "v": -55.8074627257133}, {"f": -2, "t": null, "l": -1, "r": -1, "v": -35.08675067163143}, {"f": -2, "t": null, "l": -1, "r": -1, "v": -138.6903109420408}, {"f": 7, "t": 772.4550170898438, "l": 9, "r": 12, "v": 61.3977454445281}, {"f": 1, "t": 27.5, "l": 10, "r": 11, "v": 136.1167059926023}, {"f": -2, "t": null, "l": -1, "r": -1, "v": 164.52076595011184}, {"f": -2, "t": null, "l": -1, "r": -1, "v": -119.51983362498356}, {"f": 9, "t": 834.8076782226562, "l": 13, "r": 14, "v": -13.321215103546132}, {"f": -2, "t": null, "l": -1, "r": -1, "v": -54.6380119249018}, {"f": -2, "t": null, "l": -1, "r": -1, "v": 151.94597218187653}]}, {"nodes": [{"f": 0, "t": 0.5, "l": 1, "r": 8, "v": 6.366462912410498e-14}, {"f": 5, "t": 100.5, "l": 2, "r": 5, "v": -52.60098040383778}, {"f": 2, "t": 36.5, "l": 3, "r": 4, "v": -100.51894089852455}, {"f": -2, "t": null, "l": -1, "r": -1, "v": -72.36482119284369}, {"f": -2, "t": null, "l": -1, "r": -1, "v": -114.59600075136498}, {"f": 5, "t": 293.0, "l": 6, "r": 7, "v": -45.03498664151881}, {"f": -2, "t": null, "l": -1, "r": -1, "v": -31.567657890873797}, {"f": -2, "t": null, "l": -1, "r": -1, "v": -82.74350714332486}, {"f": 8, "t": 773.2478637695312, "l": 9, "r": 12, "v": 14.836173960056898}, {"f": 6, "t": 736.2349853515625, "l": 10, "r": 11, "v": -0.10649368675862458}, {"f": -2, "t": null, "l": -1, "r": -1, "v": 11.846161280088872}, {"f": -2, "t": null, "l": -1, "r": -1, "v": -46.99767855669881}, {"f": 9, "t": 737.501953125, "l": 13, "r": 14, "v": 83.14551177407068}, {"f": -2, "t": null, "l": -1, "r": -1, "v": 305.1213436578935}, {"f": -2, "t": null, "l": -1, "r": -1, "v": 46.14953979343355}]}, {"nodes": [{"f": 9, "t": 834.8076782226562, "l": 1, "r": 8, "v": 5.1159076974727215e-14}, {"f": 0, "t": 2.5, "l": 2, "r": 5, "v": -4.6817913671506455}, {"f": 6, "t": 424.27000427246094, "l": 3, "r": 4, "v": -20.082955542630565}, {"f": -2, "t": null, "l": -1, "r": -1, "v": 30.806018839179334}, {"f": -2, "t": null, "l": -1, "r": -1, "v": -35.741101506264386}, {"f": 9, "t": 656.3992614746094, "l": 6, "r": 7, "v": 31.431283251216055}, {"f": -2, "t": null, "l": -1, "r": -1, "v": -0.9218827233676437}, {"f": -2, "t": null, "l": -1, "r": -1, "v": 116.35834393449828}, {"f": 3, "t": 6.5, "l": 9, "r": 12, "v": 151.37792087120602}, {"f": 5, "t": 351.0, "l": 10, "r": 11, "v": 275.7180917864006}, {"f": -2, "t": null, "l": -1, "r": -1, "v": 361.57526292787406}, {"f": -2, "t": null, "l": -1, "r": -1, "v": 189.8609206449271}, {"f": -2, "t": null, "l": -1, "r": -1, "v": -97.30242095918311}]}, {"nodes": [{"f": 8, "t": 645.1964416503906, "l": 1, "r": 8, "v": 6.252776074688882e-14}, {"f": 1, "t": 22.5, "l": 2, "r": 5, "v": -22.152035364415237}, {"f": 7, "t": 758.4599914550781, "l": 3, "r": 4, "v": -11.408430126399658}, {"f": -2, "t": null, "l": -1, "r": -1, "v": -4.699583413407852}, {"f": -2, "t": null, "l": -1, "r": -1, "v": -76.81968557806977}, {"f": 7, "t": 619.6449890136719, "l": 6, "r": 7, "v": -57.68857576708214}, {"f": -2, "t": null, "l": -1, "r": -1, "v": -105.22659222515153}, {"f": -2, "t": null, "l": -1, "r": -1, "v": -2.2275565660011885}, {"f": 1, "t": 7.5, "l": 9, "r": 12, "v": 28.193499554710435}, {"f": 7, "t": 431.44500732421875, "l": 10, "r": 11, "v": -50.94742924455856}, {"f": -2, "t": null, "l": -1, "r": -1, "v": 48.98171547011384}, {"f": -2, "t": null, "l": -1, "r": -1, "v": -63.438572333892616}, {"f": 9, "t": 834.8076782226562, "l": 13, "r": 14, "v": 48.54402410309389}, {"f": -2, "t": null, "l": -1, "r": -1, "v": 36.44691752705347}, {"f": -2, "t": null, "l": -1, "r": -1, "v": 248.14628260776055}]}, {"nodes": [{"f": 8, "t": 645.1964416503906, "l": 1, "r": 8, "v": 3.751665644813329e-14}, {"f": 8, "t": 522.6421508789062, "l": 2, "r": 5, "v": -19.936831827973727}, {"f": 1, "t": 20.0, "l": 3, "r": 4, "v": -54.56408669634171}, {"f": -2, "t": null, "l": -1, "r": -1, "v": -24.467593988063363}, {"f": -2, "t": null, "l": -1, "r": -1, "v": -102.71847502958705}, {"f": 2, "t": 7.5, "l": 6, "r": 7, "v": -9.468126867769447}, {"f": -2, "t": null, "l": -1, "r": -1, "v": 42.36854342055187}, {"f": -2, "t": null, "l": -1, "r": -1, "v": -19.547479423831923}, {"f": 7, "t": 837.8499755859375, "l": 9, "r": 12, "v": 25.374149599239367}, {"f": 1, "t": 7.0, "l": 10, "r": 11, "v": 53.77359734978263}, {"f": -2, "t": null, "l": -1, "r": -1, "v": -53.00183096045553}, {"f": -2, "t": null, "l": -1, "r": -1, "v": 76.01847824774892}, {"f": 9, "t": 834.8076782226562, "l": 13, "r": 14, "v": -29.5314493851443}, {"f": -2, "t": null, "l": -1, "r": -1, "v": -50.949732886276884}, {"f": -2, "t": null, "l": -1, "r": -1, "v": 109.68739337221751}]}, {"nodes": [{"f": 0, "t": 0.5, "l": 1, "r": 6, "v": 3.183231456205249e-14}, {"f": 3, "t": 11.5, "l": 2, "r": 5, "v": -39.950207172816185}, {"f": 6, "t": 651.8450012207031, "l": 3, "r": 4, "v": -43.933736173987114}, {"f": -2, "t": null, "l": -1, "r": -1, "v": -68.13309599082265}, {"f": -2, "t": null, "l": -1, "r": -1, "v": -31.834056265569338}, {"f": -2, "t": null, "l": -1, "r": -1, "v": 43.70390185177314}, {"f": 0, "t": 1.5, "l": 7, "r": 10, "v": 11.268007151307168}, {"f": 9, "t": 565.3026428222656, "l": 8, "r": 9, "v": 50.95481636647845}, {"f": -2, "t": null, "l": -1, "r": -1, "v": -33.4010572133884}, {"f": -2, "t": null, "l": -1, "r": -1, "v": 121.25137768303414}, {"f": 0, "t": 2.5, "l": 11, "r": 12, "v": -4.3232393260815485}, {"f": -2, "t": null, "l": -1, "r": -1, "v": -44.78189357615202}, {"f": -2, "t": null, "l": -1, "r": -1, "v": 30.7409276906462}]}, {"nodes": [{"f": 0, "t": 0.5, "l": 1, "r": 6, "v": 3.865352482534945e-14}, {"f": 3, "t": 11.5, "l": 2, "r": 5, "v": -35.95518645553457}, {"f": 6, "t": 651.8450012207031, "l": 3, "r": 4, "v": -39.54036255658839}, {"f": -2, "t": null, "l": -1, "r": -1, "v": -61.31978639174036}, {"f": -2, "t": null, "l": -1, "r": -1, "v": -28.65065063901242}, {"f": -2, "t": null, "l": -1, "r": -1, "v": 39.33351166659577}, {"f": 0, "t": 1.5, "l": 7, "r": 10, "v": 10.141206436176468}, {"f": 9, "t": 565.3026428222656, "l": 8, "r": 9, "v": 45.85933472983065}, {"f": -2, "t": null, "l": -1, "r": -1, "v": -30.060951492049508}, {"f": -2, "t": null, "l": -1, "r": -1, "v": 109.12623991473079}, {"f": 0, "t": 2.5, "l": 11, "r": 12, "v": -3.89091539347339}, {"f": -2, "t": null, "l": -1, "r": -1, "v": -40.30370421853684}, {"f": -2, "t": null, "l": -1, "r": -1, "v": 27.666834921581607}]}, {"nodes": [{"f": 1, "t": 26.5, "l": 1, "r": 8, "v": 5.684341886080802e-14}, {"f": 8, "t": 773.2478637695312, "l": 2, "r": 5, "v": 6.4910058291640516}, {"f": 1, "t": 24.5, "l": 3, "r": 4, "v": -2.9388575076575254}, {"f": -2, "t": null, "l": -1, "r": -1, "v": -8.988040615469515}, {"f": -2, "t": null, "l": -1, "r": -1, "v": 80.53986938014793}, {"f": 7, "t": 764.7900085449219, "l": 6, "r": 7, "v": 56.33456918093525}, {"f": -2, "t": null, "l": -1, "r": -1, "v": 153.60475640139316}, {"f": -2, "t": null, "l": -1, "r": -1, "v": -16.61807123440819}, {"f": 2, "t": 46.0, "l": 9, "r": 12, "v": -47.60070941386923}, {"f": 9, "t": 664.4375, "l": 10, "r": 11, "v": -35.23402518319135}, {"f": -2, "t": null, "l": -1, "r": -1, "v": -9.089119826871794}, {"f": -2, "t": null, "l": -1, "r": -1, "v": -104.9537728000435}, {"f": -2, "t": null, "l": -1, "r": -1, "v": -183.634235951326}]}, {"nodes": [{"f": 7, "t": 209.2300033569336, "l": 1, "r": 2, "v": 3.183231456205249e-14}, {"f": -2, "t": null, "l": -1, "r": -1, "v": -167.6904923002852}, {"f": 8, "t": 645.1964416503906, "l": 3, "r": 6, "v": 1.6938433565685707}, {"f": 5, "t": 39.0, "l": 4, "r": 5, "v": -14.164385879363419}, {"f": -2, "t": null, "l": -1, "r": -1, "v": 117.57759676538865}, {"f": -2, "t": null, "l": -1, "r": -1, "v": -16.55969465472255}, {"f": 1, "t": 7.5, "l": 7, "r": 8, "v": 22.34642096615441}, {"f": -2, "t": null, "l": -1, "r": -1, "v": -47.01773466603914}, {"f": -2, "t": null, "l": -1, "r": -1, "v": 40.70752098644095}]}, {"nodes": [{"f": 0, "t": 0.5, "l": 1, "r": 6, "v": 1.9895196601282804e-14}, {"f": 2, "t": 49.0, "l": 2, "r": 5, "v": -30.61756798017386}, {"f": 7, "t": 588.8999938964844, "l": 3, "r": 4, "v": -33.882925218608584}, {"f": -2, "t": null, "l": -1, "r": -1, "v": -50.82334209497116}, {"f": -2, "t": null, "l": -1, "r": -1, "v": -21.177612561336648}, {"f": -2, "t": null, "l": -1, "r": -1, "v": 37.95493402695536}, {"f": 1, "t": 26.5, "l": 7, "r": 10, "v": 8.635724302100352}, {"f": 1, "t": 7.5, "l": 8, "r": 9, "v": 15.286837998796974}, {"f": -2, "t": null, "l": -1, "r": -1, "v": -27.202374323599468}, {"f": -2, "t": null, "l": -1, "r": -1, "v": 26.87480499581418}, {"f": 6, "t": 950.72998046875, "l": 11, "r": 12, "v": -49.56152054399514}, {"f": -2, "t": null, "l": -1, "r": -1, "v": -66.49407898003045}, {"f": -2, "t": null, "l": -1, "r": -1, "v": 68.96638850825207}]}, {"nodes": [{"f": 9, "t": 834.8076782226562, "l": 1, "r": 8, "v": 2.5579538487363607e-14}, {"f": 7, "t": 837.8499755859375, "l": 2, "r": 5, "v": -2.7407014958077522}, {"f": 8, "t": 644.1792907714844, "l": 3, "r": 4, "v": 4.996544743964261}, {"f": -2, "t": null, "l": -1, "r": -1, "v": -10.985207314664134}, {"f": -2, "t": null, "l": -1, "r": -1, "v": 35.818495142747594}, {"f": 7, "t": 1012.2350158691406, "l": 6, "r": 7, "v": -45.03764760656142}, {"f": -2, "t": null, "l": -1, "r": -1, "v": -61.36399704198175}, {"f": -2, "t": null, "l": -1, "r": -1, "v": -12.384948735720798}, {"f": 1, "t": 12.5, "l": 9, "r": 10, "v": 88.61601503111812}, {"f": -2, "t": null, "l": -1, "r": -1, "v": -106.15100470446919}, {"f": 6, "t": 1035.8949890136719, "l": 11, "r": 12, "v": 185.99952489891177}, {"f": -2, "t": null, "l": -1, "r": -1, "v": 110.49886799529577}, {"f": -2, "t": null, "l": -1, "r": -1, "v": 261.5001818025278}]}, {"nodes": [{"f": 7, "t": 209.2300033569336, "l": 1, "r": 2, "v": 4.945377440890297e-14}, {"f": -2, "t": null, "l": -1, "r": -1, "v": -157.19077308411283}, {"f": 1, "t": 26.5, "l": 3, "r": 6, "v": 1.5877855867082609}, {"f": 6, "t": 1195.1649780273438, "l": 4, "r": 5, "v": 7.20106155005745}, {"f": -2, "t": null, "l": -1, "r": -1, "v": 3.7354604882450824}, {"f": -2, "t": null, "l": -1, "r": -1, "v": 104.23789128080382}, {"f": 3, "t": 10.5, "l": 7, "r": 8, "v": -39.108465147573376}, {"f": -2, "t": null, "l": -1, "r": -1, "v": -28.494060682693533}, {"f": -2, "t": null, "l": -1, "r": -1, "v": -155.86691426125168}]}, {"nodes": [{"f": 7, "t": 209.2300033569336, "l": 1, "r": 2, "v": 2.1600499167107046e-14}, {"f": -2, "t": null, "l": -1, "r": -1, "v": -141.4716957757015}, {"f": 0, "t": 0.5, "l": 3, "r": 6, "v": 1.4290070280374145}, {"f": 5, "t": 100.5, "l": 4, "r": 5, "v": -25.72538009592263}, {"f": -2, "t": null, "l": -1, "r": -1, "v": -61.94489478697401}, {"f": -2, "t": null, "l": -1, "r": -1, "v": -20.006509355230314}, {"f": 5, "t": 256.5, "l": 7, "r": 8, "v": 9.187403349168855}, {"f": -2, "t": null, "l": -1, "r": -1, "v": -5.576630722665824}, {"f": -2, "t": null, "l": -1, "r": -1, "v": 32.317723395043195}]}, {"nodes": [{"f": 7, "t": 837.8499755859375, "l": 1, "r": 8, "v": 1.0231815394945442e-14}, {"f": 8, "t": 773.2478637695312, "l": 2, "r": 5, "v": 6.0500734481277405}, {"f": 7, "t": 760.6749877929688, "l": 3, "r": 4, "v": -0.8539639345073893}, {"f": -2, "t": null, "l": -1, "r": -1, "v": -8.033619689627752}, {"f": -2, "t": null, "l": -1, "r": -1, "v": 59.27565301462565}, {"f": 2, "t": 20.5, "l": 6, "r": 7, "v": 70.77542391033208}, {"f": -2, "t": null, "l": -1, "r": -1, "v": 215.58666244174424}, {"f": -2, "t": null, "l": -1, "r": -1, "v": 22.505011066528027}, {"f": 6, "t": 1195.1649780273438, "l": 9, "r": 12, "v": -29.53859389380008}, {"f": 6, "t": 1001.4450073242188, "l": 10, "r": 11, "v": -46.43465571372117}, {"f": -2, "t": null, "l": -1, "r": -1, "v": -34.8518805320604}, {"f": -2, "t": null, "l": -1, "r": -1, "v": -115.93130680368586}, {"f": 1, "t": 24.5, "l": 13, "r": 14, "v": 49.30969459916505}, {"f": -2, "t": null, "l": -1, "r": -1, "v": 221.6946021546903}, {"f": -2, "t": null, "l": -1, "r": -1, "v": -36.88275917859758}]}, {"nodes": [{"f": 1, "t": 7.5, "l": 1, "r": 8, "v": 1.8758328224066646e-14}, {"f": 7, "t": 490.06500244140625, "l": 2, "r": 5, "v": -26.47251894136111}, {"f": 0, "t": 2.5, "l": 3, "r": 4, "v": 22.229287365683398}, {"f": -2, "t": null, "l": -1, "r": -1, "v": 10.276397704450384}, {"f": -2, "t": null, "l": -1, "r": -1, "v": 40.15862185753292}, {"f": 6, "t": 882.3199768066406, "l": 6, "r": 7, "v": -43.866021193876996}, {"f": -2, "t": null, "l": -1, "r": -1, "v": -34.11642386072983}, {"f": -2, "t": null, "l": -1, "r": -1, "v": -102.36360519276002}, {"f": 9, "t": 834.8076782226562, "l": 9, "r": 12, "v": 6.209603208467438}, {"f": 1, "t": 11.5, "l": 10, "r": 11, "v": 2.65645007906148}, {"f": -2, "t": null, "l": -1, "r": -1, "v": 53.312574118220596}, {"f": -2, "t": null, "l": -1, "r": -1, "v": -4.685017172990564}, {"f": 0, "t": 2.0, "l": 13, "r": 14, "v": 146.55915182000297}, {"f": -2, "t": null, "l": -1, "r": -1, "v": 199.52514193922116}, {"f": -2, "t": null, "l": -1, "r": -1, "v": 93.59316170078478}]}, {"nodes": [{"f": 7, "t": 209.2300033569336, "l": 1, "r": 2, "v": 2.870592652470805e-14}, {"f": -2, "t": null, "l": -1, "r": -1, "v": -126.05266251186947}, {"f": 8, "t": 566.7742919921875, "l": 3, "r": 6, "v": 1.2732592172916406}, {"f": 5, "t": 214.0, "l": 4, "r": 5, "v": -16.879591748426872}, {"f": -2, "t": null, "l": -1, "r": -1, "v": -21.89401446853677}, {"f": -2, "t": null, "l": -1, "r": -1, "v": 148.59635801519983}, {"f": 7, "t": 837.8499755859375, "l": 7, "r": 8, "v": 10.768596645513632}, {"f": -2, "t": null, "l": -1, "r": -1, "v": 24.071662729914916}, {"f": -2, "t": null, "l": -1, "r": -1, "v": -26.793001710442933}]}, {"nodes": [{"f": 1, "t": 26.5, "l": 1, "r": 8, "v": 2.7853275241795927e-14}, {"f": 1, "t": 7.5, "l": 2, "r": 5, "v": 4.634161692513303}, {"f": 7, "t": 490.06500244140625, "l": 3, "r": 4, "v": -23.926191051818606}, {"f": -2, "t": null, "l": -1, "r": -1, "v": 19.437819444061642}, {"f": -2, "t": null, "l": -1, "r": -1, "v": -39.41333765749012}, {"f": 8, "t": 566.7742919921875, "l": 6, "r": 7, "v": 12.498606651097454}, {"f": -2, "t": null, "l": -1, "r": -1, "v": -16.043274210513644}, {"f": -2, "t": null, "l": -1, "r": -1, "v": 29.756488102304164}, {"f": 9, "t": 664.4375, "l": 9, "r": 12, "v": -33.98385241176399}, {"f": 8, "t": 520.8550109863281, "l": 10, "r": 11, "v": -14.689444203484141}, {"f": -2, "t": null, "l": -1, "r": -1, "v": -136.2612946297445}, {"f": -2, "t": null, "l": -1, "r": -1, "v": 0.5070370997984028}, {"f": 5, "t": 339.5, "l": 13, "r": 14, "v": -91.86707703660353}, {"f": -2, "t": null, "l": -1, "r": -1, "v": -114.89540195620663}, {"f": -2, "t": null, "l": -1, "r": -1, "v": -45.81042719739736}]}, {"nodes": [{"f": 7, "t": 209.2300033569336, "l": 1, "r": 2, "v": 3.495870259939693e-14}, {"f": -2, "t": null, "l": -1, "r": -1, "v": -116.42304507091296}, {"f": 1, "t": 26.5, "l": 3, "r": 6, "v": 1.1759903542516823}, {"f": 7, "t": 248.23500061035156, "l": 4, "r": 5, "v": 5.556881047332961}, {"f": -2, "t": null, "l": -1, "r": -1, "v": 140.8455739593362}, {"f": -2, "t": null, "l": -1, "r": -1, "v": 3.9837567111468766}, {"f": 5, "t": 280.0, "l": 7, "r": 8, "v": -30.585467170587602}, {"f": -2, "t": null, "l": -1, "r": -1, "v": -13.220499783135734}, {"f": -2, "t": null, "l": -1, "r": -1, "v": -82.6803693329432}]}, {"nodes": [{"f": 7, "t": 837.8499755859375, "l": 1, "r": 8, "v": 4.661160346586257e-14}, {"f": 8, "t": 773.2478637695312, "l": 2, "r": 5, "v": 5.017871389618941}, {"f": 7, "t": 619.8849792480469, "l": 3, "r": 4, "v": -0.8520266432346769}, {"f": -2, "t": null, "l": -1, "r": -1, "v": -16.669077531989863}, {"f": -2, "t": null, "l": -1, "r": -1, "v": 19.278765396999198}, {"f": 9, "t": 737.501953125, "l": 6, "r": 7, "v": 60.0481654476216}, {"f": -2, "t": null, "l": -1, "r": -1, "v": 188.71530716053212}, {"f": -2, "t": null, "l": -1, "r": -1, "v": 17.159118209984758}, {"f": 6, "t": 1195.1649780273438, "l": 9, "r": 12, "v": -24.499019137551024}, {"f": 8, "t": 926.22998046875, "l": 10, "r": 11, "v": -38.91020865716183}, {"f": -2, "t": null, "l": -1, "r": -1, "v": -24.74312086687378}, {"f": -2, "t": null, "l": -1, "r": -1, "v": -90.85619722155134}, {"f": 6, "t": 1223.8099975585938, "l": 13, "r": 14, "v": 42.75319862063274}, {"f": -2, "t": null, "l": -1, "r": -1, "v": 178.8779034349982}, {"f": -2, "t": null, "l": -1, "r": -1, "v": -25.309153786549984}]}, {"nodes": [{"f": 0, "t": 2.5, "l": 1, "r": 8, "v": 4.5474735088646414e-14}, {"f": 0, "t": 1.5, "l": 2, "r": 5, "v": -6.82578858279677}, {"f": 7, "t": 619.2699890136719, "l": 3, "r": 4, "v": 6.601492213583973}, {"f": -2, "t": null, "l": -1, "r": -1, "v": -21.331154292358484}, {"f": -2, "t": null, "l": -1, "r": -1, "v": 34.53413871952643}, {"f": 6, "t": 617.2250061035156, "l": 6, "r": 7, "v": -29.548879161287257}, {"f": -2, "t": null, "l": -1, "r": -1, "v": 9.830659480674862}, {"f": -2, "t": null, "l": -1, "r": -1, "v": -75.49167424357641}, {"f": 5, "t": 278.5, "l": 9, "r": 12, "v": 15.926840026525948}, {"f": 6, "t": 629.22998046875, "l": 10, "r": 11, "v": -3.940528969411787}, {"f": -2, "t": null, "l": -1, "r": -1, "v": -39.0089085338009}, {"f": -2, "t": null, "l": -1, "r": -1, "v": 38.14152650785515}, {"f": 6, "t": 608.9300231933594, "l": 13, "r": 14, "v": 70.56210476535472}, {"f": -2, "t": null, "l": -1, "r": -1, "v": 192.3415371519327}, {"f": -2, "t": null, "l": -1, "r": -1, "v": 53.16504299584358}]}, {"nodes": [{"f": 7, "t": 837.8499755859375, "l": 1, "r": 8, "v": 3.8937741919653493e-14}, {"f": 9, "t": 616.00732421875, "l": 2, "r": 5, "v": 4.742405097308247}, {"f": 7, "t": 794.5800170898438, "l": 3, "r": 4, "v": -5.412896715092627}, {"f": -2, "t": null, "l": -1, "r": -1, "v": -10.253823178562612}, {"f": -2, "t": null, "l": -1, "r": -1, "v": 130.13304426206696}, {"f": 1, "t": 27.0, "l": 6, "r": 7, "v": 28.302705302078277}, {"f": -2, "t": null, "l": -1, "r": -1, "v": 40.60383836717128}, {"f": -2, "t": null, "l": -1, "r": -1, "v": -61.905603841937115}, {"f": 6, "t": 1195.1649780273438, "l": 9, "r": 12, "v": -23.15409547509298}, {"f": 6, "t": 1001.4450073242188, "l": 10, "r": 11, "v": -36.406828502338676}, {"f": -2, "t": null, "l": -1, "r": -1, "v": -26.35187391344591}, {"f": -2, "t": null, "l": -1, "r": -1, "v": -96.73655603569526}, {"f": 9, "t": 834.8076782226562, "l": 13, "r": 14, "v": 38.69199198538695}, {"f": -2, "t": null, "l": -1, "r": -1, "v": -20.730361631692517}, {"f": -2, "t": null, "l": -1, "r": -1, "v": 157.53669921954588}]}, {"nodes": [{"f": 7, "t": 209.2300033569336, "l": 1, "r": 2, "v": 3.609557097661309e-14}, {"f": -2, "t": null, "l": -1, "r": -1, "v": -99.62504922298217}, {"f": 1, "t": 6.5, "l": 3, "r": 6, "v": 1.0063136285150078}, {"f": 7, "t": 490.06500244140625, "l": 4, "r": 5, "v": -22.82133205853517}, {"f": -2, "t": null, "l": -1, "r": -1, "v": 17.804389784905787}, {"f": -2, "t": null, "l": -1, "r": -1, "v": -41.28756926009924}, {"f": 9, "t": 834.8076782226562, "l": 7, "r": 8, "v": 5.599594724813838}, {"f": -2, "t": null, "l": -1, "r": -1, "v": 3.1558454079368805}, {"f": -2, "t": null, "l": -1, "r": -1, "v": 104.5714420583306}]}, {"nodes": [{"f": 5, "t": 39.0, "l": 1, "r": 2, "v": 3.922195901395753e-14}, {"f": -2, "t": null, "l": -1, "r": -1, "v": 98.46822015557825}, {"f": 5, "t": 97.5, "l": 3, "r": 6, "v": -0.9946284864199422}, {"f": 6, "t": 285.00499725341797, "l": 4, "r": 5, "v": -28.93651139867624}, {"f": -2, "t": null, "l": -1, "r": -1, "v": -181.05690691723032}, {"f": -2, "t": null, "l": -1, "r": -1, "v": -18.07076886163666}, {"f": 5, "t": 109.0, "l": 7, "r": 8, "v": 3.994993462197254}, {"f": -2, "t": null, "l": -1, "r": -1, "v": 79.49101837669785}, {"f": -2, "t": null, "l": -1, "r": -1, "v": 0.22019221647222373}]}, {"nodes": [{"f": 8, "t": 522.6421508789062, "l": 1, "r": 6, "v": 1.1937117960769683e-14}, {"f": 8, "t": 522.0150146484375, "l": 2, "r": 5, "v": -25.415808437799555}, {"f": 1, "t": 23.5, "l": 3, "r": 4, "v": -15.136717321756796}, {"f": -2, "t": null, "l": -1, "r": -1, "v": 1.887181910599332}, {"f": -2, "t": null, "l": -1, "r": -1, "v": -66.20841501882518}, {"f": -2, "t": null, "l": -1, "r": -1, "v": -148.76490183031268}, {"f": 6, "t": 275.5950012207031, "l": 7, "r": 10, "v": 3.7977644792114402}, {"f": 5, "t": 101.5, "l": 8, "r": 9, "v": -59.901295780613225}, {"f": -2, "t": null, "l": -1, "r": -1, "v": -162.95121622550732}, {"f": -2, "t": null, "l": -1, "r": -1, "v": -25.55132229898186}, {"f": 6, "t": 375.56500244140625, "l": 11, "r": 12, "v": 6.867598708600582}, {"f": -2, "t": null, "l": -1, "r": -1, "v": 53.36023778035596}, {"f": -2, "t": null, "l": -1, "r": -1, "v": 1.9083838742800088}]}, {"nodes": [{"f": 7, "t": 837.8499755859375, "l": 1, "r": 8, "v": 5.4001247917767615e-15}, {"f": 8, "t": 747.394287109375, "l": 2, "r": 5, "v": 4.346392247049727}, {"f": 8, "t": 734.1271362304688, "l": 3, "r": 4, "v": -1.0096956563832649}, {"f": -2, "t": null, "l": -1, "r": -1, "v": 1.742637361970115}, {"f": -2, "t": null, "l": -1, "r": -1, "v": -97.34135129875153}, {"f": 9, "t": 737.501953125, "l": 6, "r": 7, "v": 39.40442216042931}, {"f": -2, "t": null, "l": -1, "r": -1, "v": 123.39826219087406}, {"f": -2, "t": null, "l": -1, "r": -1, "v": 7.906732149012527}, {"f": 7, "t": 1012.2350158691406, "l": 9, "r": 12, "v": -21.220620970889815}, {"f": 8, "t": 958.8628540039062, "l": 10, "r": 11, "v": -41.53857351392347}, {"f": -2, "t": null, "l": -1, "r": -1, "v": -30.015647850764545}, {"f": -2, "t": null, "l": -1, "r": -1, "v": -145.24490448235383}, {"f": 7, "t": 1181.2849731445312, "l": 13, "r": 14, "v": 7.80502551915827}, {"f": -2, "t": null, "l": -1, "r": -1, "v": 52.68116271471187}, {"f": -2, "t": null, "l": -1, "r": -1, "v": -25.85207737750693}]}, {"nodes": [{"f": 1, "t": 26.5, "l": 1, "r": 8, "v": 2.899014361901209e-14}, {"f": 1, "t": 24.5, "l": 2, "r": 5, "v": 3.5017200451587454}, {"f": 4, "t": 1.5, "l": 3, "r": 4, "v": -0.4081572739866559}, {"f": -2, "t": null, "l": -1, "r": -1, "v": -18.75033577378906}, {"f": -2, "t": null, "l": -1, "r": -1, "v": 5.605671742342003}, {"f": 2, "t": 19.5, "l": 6, "r": 7, "v": 48.744586166698376}, {"f": -2, "t": null, "l": -1, "r": -1, "v": 123.29530048766549}, {"f": -2, "t": null, "l": -1, "r": -1, "v": -7.168449574026951}, {"f": 3, "t": 10.5, "l": 9, "r": 12, "v": -25.679280331163884}, {"f": 9, "t": 664.4375, "l": 10, "r": 11, "v": -17.696040628340235}, {"f": -2, "t": null, "l": -1, "r": -1, "v": 0.3928804970695978}, {"f": -2, "t": null, "l": -1, "r": -1, "v": -65.93316362943312}, {"f": -2, "t": null, "l": -1, "r": -1, "v": -113.49491706222403}]}, {"nodes": [{"f": 1, "t": 7.5, "l": 1, "r": 8, "v": 3.2684965844964606e-14}, {"f": 6, "t": 882.3199768066406, "l": 2, "r": 5, "v": -18.97123833308002}, {"f": 7, "t": 614.8800048828125, "l": 3, "r": 4, "v": -11.355191956410911}, {"f": -2, "t": null, "l": -1, "r": -1, "v": 13.070931110673948}, {"f": -2, "t": null, "l": -1, "r": -1, "v": -24.678531811184474}, {"f": 4, "t": 1.5, "l": 6, "r": 7, "v": -83.70763253476741}, {"f": -2, "t": null, "l": -1, "r": -1, "v": -88.33657089848055}, {"f": -2, "t": null, "l": -1, "r": -1, "v": -79.07869417105428}, {"f": 1, "t": 11.5, "l": 9, "r": 12, "v": 4.450043559611403}, {"f": 0, "t": 0.5, "l": 10, "r": 11, "v": 42.929796427642636}, {"f": -2, "t": null, "l": -1, "r": -1, "v": -39.448135028685144}, {"f": -2, "t": null, "l": -1, "r": -1, "v": 63.52427929172458}, {"f": 9, "t": 551.0926818847656, "l": 13, "r": 14, "v": -0.9696399429282085}, {"f": -2, "t": null, "l": -1, "r": -1, "v": -30.776776852548984}, {"f": -2, "t": null, "l": -1, "r": -1, "v": 8.41408834343389}]}, {"nodes": [{"f": 5, "t": 39.0, "l": 1, "r": 2, "v": 3.637978807091713e-14}, {"f": -2, "t": null, "l": -1, "r": -1, "v": 86.85432000781793}, {"f": 5, "t": 97.5, "l": 3, "r": 6, "v": -0.8773163637152959}, {"f": 6, "t": 285.00499725341797, "l": 4, "r": 5, "v": -26.921766538697355}, {"f": -2, "t": null, "l": -1, "r": -1, "v": -148.23233434773113}, {"f": -2, "t": null, "l": -1, "r": -1, "v": -18.25672598090923}, {"f": 5, "t": 109.0, "l": 7, "r": 8, "v": 3.7734783103886436}, {"f": -2, "t": null, "l": -1, "r": -1, "v": 70.75567013490912}, {"f": -2, "t": null, "l": -1, "r": -1, "v": 0.42436871916261937}]}, {"nodes": [{"f": 1, "t": 26.5, "l": 1, "r": 8, "v": 3.751665644813329e-14}, {"f": 1, "t": 24.5, "l": 2, "r": 5, "v": 3.1405452735508947}, {"f": 8, "t": 773.2478637695312, "l": 3, "r": 4, "v": -0.3743603064630747}, {"f": -2, "t": null, "l": -1, "r": -1, "v": -4.373754018632893}, {"f": -2, "t": null, "l": -1, "r": -1, "v": 22.622153538513377}, {"f": 2, "t": 19.5, "l": 6, "r": 7, "v": 43.813024127998276}, {"f": -2, "t": null, "l": -1, "r": -1, "v": 110.08192473263932}, {"f": -2, "t": null, "l": -1, "r": -1, "v": -5.888651325482513}, {"f": 6, "t": 396.7550048828125, "l": 9, "r": 10, "v": -23.030665339372927}, {"f": -2, "t": null, "l": -1, "r": -1, "v": 59.834485217946394}, {"f": 2, "t": 16.0, "l": 11, "r": 12, "v": -30.563860844583772}, {"f": -2, "t": null, "l": -1, "r": -1, "v": 10.55449573097591}, {"f": -2, "t": null, "l": -1, "r": -1, "v": -45.983244560418655}]}, {"nodes": [{"f": 7, "t": 837.8499755859375, "l": 1, "r": 8, "v": 2.2168933355715127e-14}, {"f": 8, "t": 773.2478637695312, "l": 2, "r": 5, "v": 3.8439182428216694}, {"f": 7, "t": 760.6749877929688, "l": 3, "r": 4, "v": -0.07771584685667866}, {"f": -2, "t": null, "l": -1, "r": -1, "v": -4.46286289666929}, {"f": -2, "t": null, "l": -1, "r": -1, "v": 36.64789069532394}, {"f": 9, "t": 737.501953125, "l": 6, "r": 7, "v": 40.60923783355618}, {"f": -2, "t": null, "l": -1, "r": -1, "v": 140.65797686148164}, {"f": -2, "t": null, "l": -1, "r": -1, "v": 7.259658157581025}, {"f": 6, "t": 1195.1649780273438, "l": 9, "r": 12, "v": -18.767365538482135}, {"f": 8, "t": 926.22998046875, "l": 10, "r": 11, "v": -29.937742422394475}, {"f": -2, "t": null, "l": -1, "r": -1, "v": -18.389385391615733}, {"f": -2, "t": null, "l": -1, "r": -1, "v": -72.28171820191653}, {"f": 5, "t": 350.5, "l": 13, "r": 14, "v": 33.36105991977545}, {"f": -2, "t": null, "l": -1, "r": -1, "v": 122.13828297686678}, {"f": -2, "t": null, "l": -1, "r": -1, "v": -11.02755160877021}]}, {"nodes": [{"f": 0, "t": 2.5, "l": 1, "r": 8, "v": -5.684341886080802e-15}, {"f": 0, "t": 1.5, "l": 2, "r": 5, "v": -5.3231389574526045}, {"f": 7, "t": 619.2699890136719, "l": 3, "r": 4, "v": 5.758520365660959}, {"f": -2, "t": null, "l": -1, "r": -1, "v": -15.868664586764174}, {"f": -2, "t": null, "l": -1, "r": -1, "v": 27.385705318086085}, {"f": 8, "t": 574.4378662109375, "l": 6, "r": 7, "v": -24.076716273490945}, {"f": -2, "t": null, "l": -1, "r": -1, "v": 24.97064954884532}, {"f": -2, "t": null, "l": -1, "r": -1, "v": -50.04296876766896}, {"f": 6, "t": 629.22998046875, "l": 9, "r": 12, "v": 12.420657567389393}, {"f": 5, "t": 292.5, "l": 10, "r": 11, "v": -18.574315077992107}, {"f": -2, "t": null, "l": -1, "r": -1, "v": -31.656033443705837}, {"f": -2, "t": null, "l": -1, "r": -1, "v": 138.40630531057263}, {"f": 7, "t": 656.0950012207031, "l": 13, "r": 14, "v": 36.12269547268113}, {"f": -2, "t": null, "l": -1, "r": -1, "v": 60.803497989493486}, {"f": -2, "t": null, "l": -1, "r": -1, "v": 0.8644061629491944}]}, {"nodes": [{"f": 7, "t": 837.8499755859375, "l": 1, "r": 8, "v": 7.389644451905042e-15}, {"f": 8, "t": 523.1628723144531, "l": 2, "r": 5, "v": 3.5514281011889235}, {"f": 2, "t": 4.5, "l": 3, "r": 4, "v": -19.191843149040672}, {"f": -2, "t": null, "l": -1, "r": -1, "v": -84.78029044537672}, {"f": -2, "t": null, "l": -1, "r": -1, "v": -8.260435266317998}, {"f": 6, "t": 275.5950012207031, "l": 6, "r": 7, "v": 8.166004876597826}, {"f": -2, "t": null, "l": -1, "r": -1, "v": -48.55732136993964}, {"f": -2, "t": null, "l": -1, "r": -1, "v": 11.65667110715398}, {"f": 6, "t": 1195.1649780273438, "l": 9, "r": 12, "v": -17.339325435216466}, {"f": 6, "t": 1001.4450073242188, "l": 10, "r": 11, "v": -27.455039285373097}, {"f": -2, "t": null, "l": -1, "r": -1, "v": -19.444424254656802}, {"f": -2, "t": null, "l": -1, "r": -1, "v": -75.51872946967089}, {"f": 5, "t": 350.5, "l": 13, "r": 14, "v": 29.867339198847827}, {"f": -2, "t": null, "l": -1, "r": -1, "v": 107.18588414737155}, {"f": -2, "t": null, "l": -1, "r": -1, "v": -8.791933275414038}]}, {"nodes": [{"f": 1, "t": 26.5, "l": 1, "r": 8, "v": 7.105427357601002e-15}, {"f": 1, "t": 24.5, "l": 2, "r": 5, "v": 2.964475774169433}, {"f": 5, "t": 64.0, "l": 3, "r": 4, "v": -0.10635466603882039}, {"f": -2, "t": null, "l": -1, "r": -1, "v": 32.416069324994844}, {"f": -2, "t": null, "l": -1, "r": -1, "v": -2.708148585321513}, {"f": 1, "t": 25.5, "l": 6, "r": 7, "v": 38.4983708680078}, {"f": -2, "t": null, "l": -1, "r": -1, "v": 99.8323289832078}, {"f": -2, "t": null, "l": -1, "r": -1, "v": -7.502097718392207}, {"f": 2, "t": 46.0, "l": 9, "r": 12, "v": -21.739489010575785}, {"f": 9, "t": 664.4375, "l": 10, "r": 11, "v": -15.01247935470023}, {"f": -2, "t": null, "l": -1, "r": -1, "v": -0.612765664275166}, {"f": -2, "t": null, "l": -1, "r": -1, "v": -53.41171586250041}, {"f": -2, "t": null, "l": -1, "r": -1, "v": -95.73659522520688}]}, {"nodes": [{"f": 5, "t": 97.5, "l": 1, "r": 8, "v": 7.105427357601002e-15}, {"f": 5, "t": 64.0, "l": 2, "r": 5, "v": -17.685795064640427}, {"f": 9, "t": 573.7117614746094, "l": 3, "r": 4, "v": 10.604285077771813}, {"f": -2, "t": null, "l": -1, "r": -1, "v": -15.041032607015884}, {"f": -2, "t": null, "l": -1, "r": -1, "v": 87.5402381321349}, {"f": 6, "t": 335.1100082397461, "l": 6, "r": 7, "v": -45.97587520705267}, {"f": -2, "t": null, "l": -1, "r": -1, "v": -125.81202576722524}, {"f": -2, "t": null, "l": -1, "r": -1, "v": -34.570710841313726}, {"f": 5, "t": 113.5, "l": 9, "r": 12, "v": 3.3687228694553277}, {"f": 8, "t": 544.335693359375, "l": 10, "r": 11, "v": 52.69623183449568}, {"f": -2, "t": null, "l": -1, "r": -1, "v": 35.506904774628225}, {"f": -2, "t": null, "l": -1, "r": -1, "v": 87.07488595423058}, {"f": 8, "t": 522.7878723144531, "l": 13, "r": 14, "v": -0.4257008970862378}, {"f": -2, "t": null, "l": -1, "r": -1, "v": -25.68824646050757}, {"f": -2, "t": null, "l": -1, "r": -1, "v": 3.289379332828665}]}, {"nodes": [{"f": 7, "t": 209.2300033569336, "l": 1, "r": 2, "v": 1.2221335055073723e-14}, {"f": -2, "t": null, "l": -1, "r": -1, "v": -76.92151127754687}, {"f": 7, "t": 248.23500061035156, "l": 3, "r": 6, "v": 0.7769849623994753}, {"f": 2, "t": 45.5, "l": 4, "r": 5, "v": 64.03872020952014}, {"f": -2, "t": null, "l": -1, "r": -1, "v": 4.591511948030188}, {"f": -2, "t": null, "l": -1, "r": -1, "v": 123.48592847101008}, {"f": 7, "t": 296.75999450683594, "l": 7, "r": 8, "v": -0.5273807127988884}, {"f": -2, "t": null, "l": -1, "r": -1, "v": -59.927883027705285}, {"f": -2, "t": null, "l": -1, "r": -1, "v": 1.3683799993789751}]}, {"nodes": [{"f": 7, "t": 837.8499755859375, "l": 1, "r": 8, "v": -9.663381206337363e-15}, {"f": 8, "t": 773.2478637695312, "l": 2, "r": 5, "v": 3.2986711862367772}, {"f": 6, "t": 736.2349853515625, "l": 3, "r": 4, "v": 0.13284346861011842}, {"f": -2, "t": null, "l": -1, "r": -1, "v": 6.333221972485909}, {"f": -2, "t": null, "l": -1, "r": -1, "v": -22.731052264431856}, {"f": 5, "t": 312.5, "l": 6, "r": 7, "v": 32.9783060389867}, {"f": -2, "t": null, "l": -1, "r": -1, "v": 119.10466895373895}, {"f": -2, "t": null, "l": -1, "r": -1, "v": 4.269518400735952}, {"f": 6, "t": 1195.1649780273438, "l": 9, "r": 12, "v": -16.10527696809726}, {"f": 8, "t": 926.22998046875, "l": 10, "r": 11, "v": -24.904496431524404}, {"f": -2, "t": null, "l": -1, "r": -1, "v": -15.139770108969357}, {"f": -2, "t": null, "l": -1, "r": -1, "v": -60.70849294755957}, {"f": 9, "t": 834.8076782226562, "l": 13, "r": 14, "v": 24.957747194562728}, {"f": -2, "t": null, "l": -1, "r": -1, "v": -10.699546537128782}, {"f": -2, "t": null, "l": -1, "r": -1, "v": 96.27233465794575}]}, {"nodes": [{"f": 1, "t": 6.5, "l": 1, "r": 8, "v": -2.5579538487363607e-14}, {"f": 6, "t": 356.50498962402344, "l": 2, "r": 5, "v": -16.138226183138293}, {"f": 5, "t": 179.0, "l": 3, "r": 4, "v": 17.030084168326834}, {"f": -2, "t": null, "l": -1, "r": -1, "v": 40.13109708560194}, {"f": -2, "t": null, "l": -1, "r": -1, "v": 11.254830939008059}, {"f": 7, "t": 431.44500732421875, "l": 6, "r": 7, "v": -31.214730888349717}, {"f": -2, "t": null, "l": -1, "r": -1, "v": 8.078173230355958}, {"f": -2, "t": null, "l": -1, "r": -1, "v": -39.9464873591732}, {"f": 1, "t": 11.5, "l": 9, "r": 12, "v": 3.0739478444072637}, {"f": 7, "t": 789.5299987792969, "l": 10, "r": 11, "v": 26.704465676325942}, {"f": -2, "t": null, "l": -1, "r": -1, "v": 45.224902931404}, {"f": -2, "t": null, "l": -1, "r": -1, "v": -14.9665181475997}, {"f": 9, "t": 551.0926818847656, "l": 13, "r": 14, "v": -1.2527666881975645}, {"f": -2, "t": null, "l": -1, "r": -1, "v": -22.53676258208721}, {"f": -2, "t": null, "l": -1, "r": -1, "v": 5.4477505376565825}]}, {"nodes": [{"f": 5, "t": 97.5, "l": 1, "r": 8, "v": -2.6432189770275728e-14}, {"f": 1, "t": 22.5, "l": 2, "r": 5, "v": -16.36587988314706}, {"f": 5, "t": 64.0, "l": 3, "r": 4, "v": 1.3157862421560962}, {"f": -2, "t": null, "l": -1, "r": -1, "v": 26.188274915443298}, {"f": -2, "t": null, "l": -1, "r": -1, "v": -28.531200165788544}, {"f": 6, "t": 335.1100082397461, "l": 6, "r": 7, "v": -55.265545358813995}, {"f": -2, "t": null, "l": -1, "r": -1, "v": -114.54575844145495}, {"f": -2, "t": null, "l": -1, "r": -1, "v": -40.445492088153756}, {"f": 5, "t": 109.0, "l": 9, "r": 12, "v": 3.1173104539327414}, {"f": 9, "t": 555.3605041503906, "l": 10, "r": 11, "v": 57.590418314307186}, {"f": -2, "t": null, "l": -1, "r": -1, "v": 38.12837452075905}, {"f": -2, "t": null, "l": -1, "r": -1, "v": 77.05246210785532}, {"f": 8, "t": 522.7878723144531, "l": 13, "r": 14, "v": 0.39365506091401914}, {"f": -2, "t": null, "l": -1, "r": -1, "v": -22.654356699014794}, {"f": -2, "t": null, "l": -1, "r": -1, "v": 3.686228169475278}]}, {"nodes": [{"f": 7, "t": 209.2300033569336, "l": 1, "r": 2, "v": -2.984279490192421e-14}, {"f": -2, "t": null, "l": -1, "r": -1, "v": -67.86965279406229}, {"f": 7, "t": 248.23500061035156, "l": 3, "r": 6, "v": 0.6855520484248417}, {"f": 3, "t": 10.5, "l": 4, "r": 5, "v": 57.54134183245219}, {"f": -2, "t": null, "l": -1, "r": -1, "v": 5.492068108957142}, {"f": -2, "t": null, "l": -1, "r": -1, "v": 109.59061555594724}, {"f": 7, "t": 296.75999450683594, "l": 7, "r": 8, "v": -0.4867322770190214}, {"f": -2, "t": null, "l": -1, "r": -1, "v": -50.73142970746369}, {"f": -2, "t": null, "l": -1, "r": -1, "v": 1.1168218962930427}]}, {"nodes": [{"f": 1, "t": 26.5, "l": 1, "r": 8, "v": -1.0516032489249483e-14}, {"f": 1, "t": 24.5, "l": 2, "r": 5, "v": 2.425877078939258}, {"f": 7, "t": 665.739990234375, "l": 3, "r": 4, "v": -0.4746328600366121}, {"f": -2, "t": null, "l": -1, "r": -1, "v": 5.751812428194084}, {"f": -2, "t": null, "l": -1, "r": -1, "v": -9.081777817296693}, {"f": 2, "t": 19.5, "l": 6, "r": 7, "v": 35.98892065851718}, {"f": -2, "t": null, "l": -1, "r": -1, "v": 89.26559053179498}, {"f": -2, "t": null, "l": -1, "r": -1, "v": -3.968581746441174}, {"f": 6, "t": 396.7550048828125, "l": 9, "r": 10, "v": -17.789765245554644}, {"f": -2, "t": null, "l": -1, "r": -1, "v": 45.349936751654354}, {"f": 4, "t": 1.5, "l": 11, "r": 12, "v": -23.529738154391826}, {"f": -2, "t": null, "l": -1, "r": -1, "v": 13.45584219707562}, {"f": -2, "t": null, "l": -1, "r": -1, "v": -37.39933078619212}]}, {"nodes": [{"f": 0, "t": 2.5, "l": 1, "r": 8, "v": -1.1652900866465642e-14}, {"f": 0, "t": 1.5, "l": 2, "r": 5, "v": -4.241979693207999}, {"f": 7, "t": 602.4599914550781, "l": 3, "r": 4, "v": 5.866128317618776}, {"f": -2, "t": null, "l": -1, "r": -1, "v": -15.475095400730728}, {"f": -2, "t": null, "l": -1, "r": -1, "v": 20.64082166109151}, {"f": 8, "t": 574.4378662109375, "l": 6, "r": 7, "v": -21.348008634607158}, {"f": -2, "t": null, "l": -1, "r": -1, "v": 18.47578524070854}, {"f": -2, "t": null, "l": -1, "r": -1, "v": -42.43119362742135}, {"f": 6, "t": 629.22998046875, "l": 9, "r": 12, "v": 9.897952617485293}, {"f": 9, "t": 695.1515808105469, "l": 10, "r": 11, "v": -16.445889458774918}, {"f": -2, "t": null, "l": -1, "r": -1, "v": -27.081186698683194}, {"f": -2, "t": null, "l": -1, "r": -1, "v": 111.17767742012438}, {"f": 7, "t": 656.0950012207031, "l": 13, "r": 14, "v": 30.043243616978398}, {"f": -2, "t": null, "l": -1, "r": -1, "v": 49.493092269848376}, {"f": -2, "t": null, "l": -1, "r": -1, "v": 2.257745541449854}]}, {"nodes": [{"f": 7, "t": 837.8499755859375, "l": 1, "r": 8, "v": -3.9790393202565614e-15}, {"f": 9, "t": 616.00732421875, "l": 2, "r": 5, "v": 2.8108782104228203}, {"f": 5, "t": 235.5, "l": 3, "r": 4, "v": -2.9903326796010994}, {"f": -2, "t": null, "l": -1, "r": -1, "v": 1.584514569107809}, {"f": -2, "t": null, "l": -1, "r": -1, "v": -64.75077053717136}, {"f": 9, "t": 630.7082214355469, "l": 6, "r": 7, "v": 16.269687475278314}, {"f": -2, "t": null, "l": -1, "r": -1, "v": 124.99305727571095}, {"f": -2, "t": null, "l": -1, "r": -1, "v": 11.739547066926953}, {"f": 1, "t": 21.5, "l": 9, "r": 12, "v": -13.723699497946733}, {"f": 8, "t": 926.22998046875, "l": 10, "r": 11, "v": -24.89875932672733}, {"f": -2, "t": null, "l": -1, "r": -1, "v": -13.716188803921924}, {"f": -2, "t": null, "l": -1, "r": -1, "v": -80.81161194075435}, {"f": 9, "t": 834.8076782226562, "l": 13, "r": 14, "v": 13.096444091126694}, {"f": -2, "t": null, "l": -1, "r": -1, "v": -4.745474072948937}, {"f": -2, "t": null, "l": -1, "r": -1, "v": 84.46411674742922}]}, {"nodes": [{"f": 1, "t": 26.5, "l": 1, "r": 8, "v": -2.2168933355715127e-14}, {"f": 1, "t": 24.5, "l": 2, "r": 5, "v": 2.294784528920429}, {"f": 7, "t": 223.65499877929688, "l": 3, "r": 4, "v": -0.16796954167270323}, {"f": -2, "t": null, "l": -1, "r": -1, "v": -58.58870410142606}, {"f": -2, "t": null, "l": -1, "r": -1, "v": 0.5622896403242137}, {"f": 1, "t": 25.5, "l": 6, "r": 7, "v": 30.792367345783823}, {"f": -2, "t": null, "l": -1, "r": -1, "v": 78.45117195160287}, {"f": -2, "t": null, "l": -1, "r": -1, "v": -4.951736108580462}, {"f": 3, "t": 10.5, "l": 9, "r": 12, "v": -16.82841987875}, {"f": 9, "t": 563.6671142578125, "l": 10, "r": 11, "v": -11.247100011572421}, {"f": -2, "t": null, "l": -1, "r": -1, "v": 15.2423354866404}, {"f": -2, "t": null, "l": -1, "r": -1, "v": -26.38392029626546}, {"f": -2, "t": null, "l": -1, "r": -1, "v": -78.2229384177034}]}, {"nodes": [{"f": 5, "t": 97.5, "l": 1, "r": 6, "v": -5.0022208597511053e-14}, {"f": 6, "t": 285.00499725341797, "l": 2, "r": 3, "v": -13.777128416625125}, {"f": -2, "t": null, "l": -1, "r": -1, "v": -106.0568086168106}, {"f": 8, "t": 602.6785888671875, "l": 4, "r": 5, "v": -7.62514973661276}, {"f": -2, "t": null, "l": -1, "r": -1, "v": 1.0161827328738298}, {"f": -2, "t": null, "l": -1, "r": -1, "v": -42.190479614559116}, {"f": 5, "t": 113.5, "l": 7, "r": 10, "v": 2.624214936499964}, {"f": 8, "t": 544.335693359375, "l": 8, "r": 9, "v": 40.938876110502065}, {"f": -2, "t": null, "l": -1, "r": -1, "v": 28.03592806564214}, {"f": -2, "t": null, "l": -1, "r": -1, "v": 66.74477220022192}, {"f": 8, "t": 597.8314208984375, "l": 11, "r": 12, "v": -0.3230666922694274}, {"f": -2, "t": null, "l": -1, "r": -1, "v": -11.6593108888653}, {"f": -2, "t": null, "l": -1, "r": -1, "v": 5.345055406028508}]}, {"nodes": [{"f": 7, "t": 837.8499755859375, "l": 1, "r": 8, "v": -4.064304448547773e-14}, {"f": 5, "t": 200.0, "l": 2, "r": 5, "v": 2.7121609172873407}, {"f": 7, "t": 456.510009765625, "l": 3, "r": 4, "v": -5.0139656707805464}, {"f": -2, "t": null, "l": -1, "r": -1, "v": 19.115927112879803}, {"f": -2, "t": null, "l": -1, "r": -1, "v": -13.30861631516379}, {"f": 7, "t": 296.75999450683594, "l": 6, "r": 7, "v": 11.017746999460318}, {"f": -2, "t": null, "l": -1, "r": -1, "v": -52.367310203595345}, {"f": -2, "t": null, "l": -1, "r": -1, "v": 16.157075961870238}, {"f": 7, "t": 1012.2350158691406, "l": 9, "r": 12, "v": -13.24172683146196}, {"f": 8, "t": 958.8628540039062, "l": 10, "r": 11, "v": -26.055876903375726}, {"f": -2, "t": null, "l": -1, "r": -1, "v": -18.156511155872902}, {"f": -2, "t": null, "l": -1, "r": -1, "v": -97.15016863090113}, {"f": 7, "t": 1181.2849731445312, "l": 13, "r": 14, "v": 5.06420184270056}, {"f": -2, "t": null, "l": -1, "r": -1, "v": 32.37140947767451}, {"f": -2, "t": null, "l": -1, "r": -1, "v": -15.416203883529903}]}, {"nodes": [{"f": 1, "t": 4.5, "l": 1, "r": 8, "v": -2.7000623958883806e-14}, {"f": 6, "t": 835.989990234375, "l": 2, "r": 5, "v": -18.055299881078735}, {"f": 1, "t": 1.5, "l": 3, "r": 4, "v": -6.752297293842702}, {"f": -2, "t": null, "l": -1, "r": -1, "v": -47.95058148337432}, {"f": -2, "t": null, "l": -1, "r": -1, "v": -0.8668281239096132}, {"f": 6, "t": 930.9349975585938, "l": 6, "r": 7, "v": -63.26731023002287}, {"f": -2, "t": null, "l": -1, "r": -1, "v": -59.127581950231615}, {"f": -2, "t": null, "l": -1, "r": -1, "v": -67.40703850981413}, {"f": 9, "t": 834.8076782226562, "l": 9, "r": 12, "v": 2.00614443123094}, {"f": 1, "t": 17.5, "l": 10, "r": 11, "v": 0.7791267169288086}, {"f": -2, "t": null, "l": -1, "r": -1, "v": 9.476184288436668}, {"f": -2, "t": null, "l": -1, "r": -1, "v": -6.468421259327741}, {"f": 6, "t": 1035.8949890136719, "l": 13, "r": 14, "v": 55.99492386052475}, {"f": -2, "t": null, "l": -1, "r": -1, "v": 39.80001810076601}, {"f": -2, "t": null, "l": -1, "r": -1, "v": 72.18982962028349}]}, {"nodes": [{"f": 1, "t": 6.5, "l": 1, "r": 8, "v": -2.7569058147491886e-14}, {"f": 6, "t": 356.50498962402344, "l": 2, "r": 5, "v": -12.74505525547277}, {"f": 7, "t": 340.88999938964844, "l": 3, "r": 4, "v": 13.118781984256453}, {"f": -2, "t": null, "l": -1, "r": -1, "v": 38.49671781217444}, {"f": -2, "t": null, "l": -1, "r": -1, "v": 6.774298027276956}, {"f": 6, "t": 835.989990234375, "l": 6, "r": 7, "v": -24.501344909895145}, {"f": -2, "t": null, "l": -1, "r": -1, "v": -17.292626177200596}, {"f": -2, "t": null, "l": -1, "r": -1, "v": -56.94057920702062}, {"f": 1, "t": 11.5, "l": 9, "r": 12, "v": 2.4276295724709707}, {"f": 0, "t": 0.5, "l": 10, "r": 11, "v": 22.01044952669204}, {"f": -2, "t": null, "l": -1, "r": -1, "v": -23.881432797386413}, {"f": -2, "t": null, "l": -1, "r": -1, "v": 35.77801422391558}, {"f": 9, "t": 536.2230224609375, "l": 13, "r": 14, "v": -1.1579571797103518}, {"f": -2, "t": null, "l": -1, "r": -1, "v": -40.161341578054675}, {"f": -2, "t": null, "l": -1, "r": -1, "v": 1.170603082877369}]}, {"nodes": [{"f": 2, "t": 9.5, "l": 1, "r": 8, "v": -1.2505552149377763e-14}, {"f": 7, "t": 621.0150146484375, "l": 2, "r": 5, "v": 11.981196821414596}, {"f": 5, "t": 224.5, "l": 3, "r": 4, "v": -17.12896111965863}, {"f": -2, "t": null, "l": -1, "r": -1, "v": -7.075142387889798}, {"f": -2, "t": null, "l": -1, "r": -1, "v": -107.61332970557811}, {"f": 6, "t": 673.2449951171875, "l": 6, "r": 7, "v": 53.56713673723349}, {"f": -2, "t": null, "l": -1, "r": -1, "v": 4.430943462269814}, {"f": -2, "t": null, "l": -1, "r": -1, "v": 90.41928169345624}, {"f": 2, "t": 11.5, "l": 9, "r": 12, "v": -2.4539800718560163}, {"f": 1, "t": 9.5, "l": 10, "r": 11, "v": -61.366082288844915}, {"f": -2, "t": null, "l": -1, "r": -1, "v": -48.93337822002621}, {"f": -2, "t": null, "l": -1, "r": -1, "v": -86.23149042648231}, {"f": 7, "t": 509.2099914550781, "l": 13, "r": 14, "v": -0.24477623871893286}, {"f": -2, "t": null, "l": -1, "r": -1, "v": 15.855775188963014}, {"f": -2, "t": null, "l": -1, "r": -1, "v": -5.611626714612915}]}, {"nodes": [{"f": 1, "t": 26.5, "l": 1, "r": 8, "v": -2.3874235921539365e-14}, {"f": 1, "t": 24.5, "l": 2, "r": 5, "v": 2.0759197114946826}, {"f": 5, "t": 64.0, "l": 3, "r": 4, "v": 0.016009697497544814}, {"f": -2, "t": null, "l": -1, "r": -1, "v": 21.637860682539316}, {"f": -2, "t": null, "l": -1, "r": -1, "v": -1.713738381305797}, {"f": 1, "t": 25.5, "l": 6, "r": 7, "v": 25.91202130203299}, {"f": -2, "t": null, "l": -1, "r": -1, "v": 67.39819849000344}, {"f": -2, "t": null, "l": -1, "r": -1, "v": -5.202611588944848}, {"f": 6, "t": 396.7550048828125, "l": 9, "r": 10, "v": -15.22341121762787}, {"f": -2, "t": null, "l": -1, "r": -1, "v": 36.902892860901716}, {"f": 3, "t": 2.5, "l": 11, "r": 12, "v": -19.96216613385783}, {"f": -2, "t": null, "l": -1, "r": -1, "v": 19.02513772648058}, {"f": -2, "t": null, "l": -1, "r": -1, "v": -28.626011436155256}]}, {"nodes": [{"f": 5, "t": 97.5, "l": 1, "r": 6, "v": -3.865352482534945e-14}, {"f": 6, "t": 285.00499725341797, "l": 2, "r": 3, "v": -12.238448058307718}, {"f": -2, "t": null, "l": -1, "r": -1, "v": -92.85794779637615}, {"f": 9, "t": 567.6304321289062, "l": 4, "r": 5, "v": -6.863814742436489}, {"f": -2, "t": null, "l": -1, "r": -1, "v": -20.255829221775382}, {"f": -2, "t": null, "l": -1, "r": -1, "v": 13.22420697657185}, {"f": 5, "t": 109.0, "l": 7, "r": 10, "v": 2.331132963487139}, {"f": 1, "t": 21.5, "l": 8, "r": 9, "v": 46.05847072472305}, {"f": -2, "t": null, "l": -1, "r": -1, "v": 29.453466510493087}, {"f": -2, "t": null, "l": -1, "r": -1, "v": 62.663474938953016}, {"f": 8, "t": 522.7878723144531, "l": 11, "r": 12, "v": 0.14476607542534267}, {"f": -2, "t": null, "l": -1, "r": -1, "v": -16.373683185472885}, {"f": -2, "t": null, "l": -1, "r": -1, "v": 2.504544541267946}]}, {"nodes": [{"f": 2, "t": 50.5, "l": 1, "r": 8, "v": -5.854872142663226e-14}, {"f": 9, "t": 536.1626586914062, "l": 2, "r": 5, "v": -0.5233883762219858}, {"f": 1, "t": 10.0, "l": 3, "r": 4, "v": -30.491088883490942}, {"f": -2, "t": null, "l": -1, "r": -1, "v": 20.04544889900339}, {"f": -2, "t": null, "l": -1, "r": -1, "v": -64.1821140718205}, {"f": 2, "t": 7.5, "l": 6, "r": 7, "v": 1.0706382465050863}, {"f": -2, "t": null, "l": -1, "r": -1, "v": 30.042165595764345}, {"f": -2, "t": null, "l": -1, "r": -1, "v": -1.260404183895084}, {"f": -2, "t": null, "l": -1, "r": -1, "v": 51.81544924597074}]}, {"nodes": [{"f": 0, "t": 2.5, "l": 1, "r": 8, "v": -6.480149750132113e-14}, {"f": 0, "t": 1.5, "l": 2, "r": 5, "v": -3.331888713595559}, {"f": 7, "t": 602.4599914550781, "l": 3, "r": 4, "v": 5.280520362399071}, {"f": -2, "t": null, "l": -1, "r": -1, "v": -12.133073384672665}, {"f": -2, "t": null, "l": -1, "r": -1, "v": 17.336085264217964}, {"f": 8, "t": 574.4378662109375, "l": 6, "r": 7, "v": -17.906734842201857}, {"f": -2, "t": null, "l": -1, "r": -1, "v": 15.880237520850407}, {"f": -2, "t": null, "l": -1, "r": -1, "v": -35.79395550499423}, {"f": 9, "t": 670.5464172363281, "l": 9, "r": 12, "v": 7.774406998389422}, {"f": 6, "t": 629.22998046875, "l": 10, "r": 11, "v": -3.517979155799837}, {"f": -2, "t": null, "l": -1, "r": -1, "v": -21.25910167641165}, {"f": -2, "t": null, "l": -1, "r": -1, "v": 17.77136786893434}, {"f": 6, "t": 659.125, "l": 13, "r": 14, "v": 38.82846892240988}, {"f": -2, "t": null, "l": -1, "r": -1, "v": 78.75834794303728}, {"f": -2, "t": null, "l": -1, "r": -1, "v": 25.518509248867417}]}, {"nodes": [{"f": 7, "t": 837.8499755859375, "l": 1, "r": 8, "v": -7.077005648170598e-14}, {"f": 8, "t": 846.471435546875, "l": 2, "r": 5, "v": 2.41198288738901}, {"f": 9, "t": 782.9949951171875, "l": 3, "r": 4, "v": 0.7067689958970413}, {"f": -2, "t": null, "l": -1, "r": -1, "v": 1.6410020674601975}, {"f": -2, "t": null, "l": -1, "r": -1, "v": -71.22917751446596}, {"f": 1, "t": 27.0, "l": 6, "r": 7, "v": 29.01331959466372}, {"f": -2, "t": null, "l": -1, "r": -1, "v": 47.370178972176205}, {"f": -2, "t": null, "l": -1, "r": -1, "v": -44.414117915386214}, {"f": 7, "t": 978.22998046875, "l": 9, "r": 12, "v": -11.776151744311464}, {"f": 8, "t": 958.8628540039062, "l": 10, "r": 11, "v": -24.296916213638003}, {"f": -2, "t": null, "l": -1, "r": -1, "v": -16.994299249616233}, {"f": -2, "t": null, "l": -1, "r": -1, "v": -82.71785192581217}, {"f": 3, "t": 6.5, "l": 13, "r": 14, "v": 2.309708283680891}, {"f": -2, "t": null, "l": -1, "r": -1, "v": 8.718487577047329}, {"f": -2, "t": null, "l": -1, "r": -1, "v": -42.551746769884176}]}, {"nodes": [{"f": 1, "t": 26.5, "l": 1, "r": 8, "v": -9.29389898374211e-14}, {"f": 1, "t": 24.5, "l": 2, "r": 5, "v": 1.7775947422936005}, {"f": 9, "t": 557.6885375976562, "l": 3, "r": 4, "v": -0.10073989778410357}, {"f": -2, "t": null, "l": -1, "r": -1, "v": 8.171671601147159}, {"f": -2, "t": null, "l": -1, "r": -1, "v": -4.236945647249735}, {"f": 2, "t": 19.5, "l": 6, "r": 7, "v": 23.512609863192747}, {"f": -2, "t": null, "l": -1, "r": -1, "v": 61.8705457476583}, {"f": -2, "t": null, "l": -1, "r": -1, "v": -5.255842050156417}, {"f": 3, "t": 10.5, "l": 9, "r": 12, "v": -13.035694776820511}, {"f": 8, "t": 604.3307189941406, "l": 10, "r": 11, "v": -8.408119625194859}, {"f": -2, "t": null, "l": -1, "r": -1, "v": 9.942971764500545}, {"f": -2, "t": null, "l": -1, "r": -1, "v": -23.70069578327436}, {"f": -2, "t": null, "l": -1, "r": -1, "v": -63.93902144470269}]}, {"nodes": [{"f": 6, "t": 275.5950012207031, "l": 1, "r": 6, "v": -8.924416761146859e-14}, {"f": 1, "t": 20.0, "l": 2, "r": 5, "v": -21.03681328090737}, {"f": 8, "t": 506.33143615722656, "l": 3, "r": 4, "v": -5.065984909436253}, {"f": -2, "t": null, "l": -1, "r": -1, "v": 34.585887818435594}, {"f": -2, "t": null, "l": -1, "r": -1, "v": -18.283275818726867}, {"f": -2, "t": null, "l": -1, "r": -1, "v": -84.92012676679184}, {"f": 6, "t": 392.4549865722656, "l": 7, "r": 10, "v": 1.1072006989950307}, {"f": 1, "t": 21.5, "l": 8, "r": 9, "v": 18.42906090499768}, {"f": -2, "t": null, "l": -1, "r": -1, "v": 5.060662430842671}, {"f": -2, "t": null, "l": -1, "r": -1, "v": 48.50795747184645}, {"f": 9, "t": 834.8076782226562, "l": 11, "r": 12, "v": -1.6389478702492917}, {"f": -2, "t": null, "l": -1, "r": -1, "v": -2.8177976554304442}, {"f": -2, "t": null, "l": -1, "r": -1, "v": 45.515043536996814}]}, {"nodes": [{"f": 2, "t": 50.5, "l": 1, "r": 8, "v": -6.480149750132113e-14}, {"f": 9, "t": 536.1626586914062, "l": 2, "r": 5, "v": -0.47623963695484506}, {"f": 1, "t": 10.0, "l": 3, "r": 4, "v": -28.05285828497125}, {"f": -2, "t": null, "l": -1, "r": -1, "v": 15.28667726421827}, {"f": -2, "t": null, "l": -1, "r": -1, "v": -56.94588198443093}, {"f": 2, "t": 7.5, "l": 6, "r": 7, "v": 0.9906017804928361}, {"f": -2, "t": null, "l": -1, "r": -1, "v": 25.689441391026826}, {"f": -2, "t": null, "l": -1, "r": -1, "v": -0.9966611766765653}, {"f": -2, "t": null, "l": -1, "r": -1, "v": 47.14772405852318}]}, {"nodes": [{"f": 7, "t": 209.2300033569336, "l": 1, "r": 2, "v": -5.2295945351943376e-14}, {"f": -2, "t": null, "l": -1, "r": -1, "v": -46.410468873472155}, {"f": 7, "t": 248.23500061035156, "l": 3, "r": 6, "v": 0.4687926148835043}, {"f": 0, "t": 1.0, "l": 4, "r": 5, "v": 49.001475846979815}, {"f": -2, "t": null, "l": -1, "r": -1, "v": 5.951180638435517}, {"f": -2, "t": null, "l": -1, "r": -1, "v": 92.05177105552411}, {"f": 7, "t": 296.75999450683594, "l": 7, "r": 8, "v": -0.5318812661906465}, {"f": -2, "t": null, "l": -1, "r": -1, "v": -37.70434867558462}, {"f": -2, "t": null, "l": -1, "r": -1, "v": 0.6544740766623528}]}, {"nodes": [{"f": 7, "t": 837.8499755859375, "l": 1, "r": 8, "v": -7.247535904753021e-14}, {"f": 8, "t": 594.3392944335938, "l": 2, "r": 5, "v": 2.071819897421469}, {"f": 5, "t": 221.0, "l": 3, "r": 4, "v": -4.393396729997044}, {"f": -2, "t": null, "l": -1, "r": -1, "v": -1.581834754547038}, {"f": -2, "t": null, "l": -1, "r": -1, "v": -62.030417226722165}, {"f": 7, "t": 703.3450012207031, "l": 6, "r": 7, "v": 9.02192777189637}, {"f": -2, "t": null, "l": -1, "r": -1, "v": 0.7475458669142863}, {"f": -2, "t": null, "l": -1, "r": -1, "v": 33.84507348684262}, {"f": 1, "t": 21.5, "l": 9, "r": 12, "v": -10.115355969764071}, {"f": 8, "t": 926.22998046875, "l": 10, "r": 11, "v": -18.05278984534222}, {"f": -2, "t": null, "l": -1, "r": -1, "v": -10.458237938989143}, {"f": -2, "t": null, "l": -1, "r": -1, "v": -56.02554937710761}, {"f": 9, "t": 834.8076782226562, "l": 13, "r": 14, "v": 8.934485331623488}, {"f": -2, "t": null, "l": -1, "r": -1, "v": -3.5226084506511057}, {"f": -2, "t": null, "l": -1, "r": -1, "v": 58.76286046072187}]}, {"nodes": [{"f": 1, "t": 25.5, "l": 1, "r": 8, "v": -6.963318810448982e-14}, {"f": 1, "t": 24.5, "l": 2, "r": 5, "v": 1.9610992122684063}, {"f": 3, "t": 3.5, "l": 3, "r": 4, "v": 0.041461935916184925}, {"f": -2, "t": null, "l": -1, "r": -1, "v": -9.49614128983078}, {"f": -2, "t": null, "l": -1, "r": -1, "v": 3.1685449607512552}, {"f": 4, "t": 1.5, "l": 6, "r": 7, "v": 53.79130567377839}, {"f": -2, "t": null, "l": -1, "r": -1, "v": 85.7061967326216}, {"f": -2, "t": null, "l": -1, "r": -1, "v": -10.038476443908053}, {"f": 8, "t": 520.8550109863281, "l": 9, "r": 12, "v": -10.295770864409569}, {"f": 5, "t": 140.5, "l": 10, "r": 11, "v": -41.53637065109305}, {"f": -2, "t": null, "l": -1, "r": -1, "v": -26.0018039529528}, {"f": -2, "t": null, "l": -1, "r": -1, "v": -57.070937349233304}, {"f": 5, "t": 50.0, "l": 13, "r": 14, "v": -5.8328280377405}, {"f": -2, "t": null, "l": -1, "r": -1, "v": -47.27952684769173}, {"f": -2, "t": null, "l": -1, "r": -1, "v": -2.644620436975021}]}, {"nodes": [{"f": 6, "t": 275.5950012207031, "l": 1, "r": 8, "v": -8.839151632855646e-14}, {"f": 7, "t": 492.9550018310547, "l": 2, "r": 5, "v": -19.38460020220733}, {"f": 9, "t": 616.6833801269531, "l": 3, "r": 4, "v": 16.311028150118943}, {"f": -2, "t": null, "l": -1, "r": -1, "v": 31.002846725972972}, {"f": -2, "t": null, "l": -1, "r": -1, "v": 1.6192095742649144}, {"f": 5, "t": 101.5, "l": 6, "r": 7, "v": -43.18168577042485}, {"f": -2, "t": null, "l": -1, "r": -1, "v": -76.55256640073168}, {"f": -2, "t": null, "l": -1, "r": -1, "v": -26.496245455271435}, {"f": 6, "t": 392.4549865722656, "l": 9, "r": 12, "v": 1.020242115905556}, {"f": 1, "t": 21.5, "l": 10, "r": 11, "v": 15.642033159261294}, {"f": -2, "t": null, "l": -1, "r": -1, "v": 4.150435352881402}, {"f": -2, "t": null, "l": -1, "r": -1, "v": 41.49812822361605}, {"f": 6, "t": 393.72499084472656, "l": 13, "r": 14, "v": -1.2978467080410854}, {"f": -2, "t": null, "l": -1, "r": -1, "v": -67.06792856750928}, {"f": -2, "t": null, "l": -1, "r": -1, "v": -0.4858703887883915}]}, {"nodes": [{"f": 5, "t": 39.0, "l": 1, "r": 2, "v": -7.418066161335446e-14}, {"f": -2, "t": null, "l": -1, "r": -1, "v": 43.93347903988331}, {"f": 5, "t": 97.5, "l": 3, "r": 6, "v": -0.4437725155544518}, {"f": 7, "t": 647.875, "l": 4, "r": 5, "v": -12.44329990845338}, {"f": -2, "t": null, "l": -1, "r": -1, "v": -24.444842425803394}, {"f": -2, "t": null, "l": -1, "r": -1, "v": 11.559785126246652}, {"f": 5, "t": 109.0, "l": 7, "r": 8, "v": 1.6990002331774992}, {"f": -2, "t": null, "l": -1, "r": -1, "v": 36.78744006148938}, {"f": -2, "t": null, "l": -1, "r": -1, "v": -0.055421758238094296}]}, {"nodes": [{"f": 7, "t": 456.510009765625, "l": 1, "r": 8, "v": -4.5758952182950455e-14}, {"f": 2, "t": 46.5, "l": 2, "r": 5, "v": 8.081456532907096}, {"f": 7, "t": 351.2050018310547, "l": 3, "r": 4, "v": 0.9308502718986691}, {"f": -2, "t": null, "l": -1, "r": -1, "v": -13.355643408935741}, {"f": -2, "t": null, "l": -1, "r": -1, "v": 20.574779083045982}, {"f": 3, "t": 11.5, "l": 6, "r": 7, "v": 53.36862951929379}, {"f": -2, "t": null, "l": -1, "r": -1, "v": 82.74205214405401}, {"f": -2, "t": null, "l": -1, "r": -1, "v": 38.68191820691368}, {"f": 7, "t": 578.760009765625, "l": 9, "r": 12, "v": -2.2793851759482138}, {"f": 1, "t": 20.0, "l": 10, "r": 11, "v": -26.01308272407374}, {"f": -2, "t": null, "l": -1, "r": -1, "v": -11.801442392797533}, {"f": -2, "t": null, "l": -1, "r": -1, "v": -54.436363386626155}, {"f": 2, "t": 9.5, "l": 13, "r": 14, "v": 2.0358325600746094}, {"f": -2, "t": null, "l": -1, "r": -1, "v": 30.22656724494197}, {"f": -2, "t": null, "l": -1, "r": -1, "v": -2.9982272050802763}]}, {"nodes": [{"f": 1, "t": 6.5, "l": 1, "r": 8, "v": -3.694822225952521e-14}, {"f": 6, "t": 835.989990234375, "l": 2, "r": 5, "v": -9.585492977049764}, {"f": 6, "t": 356.50498962402344, "l": 3, "r": 4, "v": -4.602759254510078}, {"f": -2, "t": null, "l": -1, "r": -1, "v": 8.788713415017265}, {"f": -2, "t": null, "l": -1, "r": -1, "v": -12.042466293136378}, {"f": 2, "t": 16.5, "l": 6, "r": 7, "v": -44.46462903482757}, {"f": -2, "t": null, "l": -1, "r": -1, "v": -46.13394594547003}, {"f": -2, "t": null, "l": -1, "r": -1, "v": -42.7953121241851}, {"f": 1, "t": 11.5, "l": 9, "r": 12, "v": 1.8258081861046729}, {"f": 0, "t": 0.5, "l": 10, "r": 11, "v": 18.139930333029216}, {"f": -2, "t": null, "l": -1, "r": -1, "v": -20.258908651249794}, {"f": -2, "t": null, "l": -1, "r": -1, "v": 29.659582028312922}, {"f": 8, "t": 566.7742919921875, "l": 13, "r": 14, "v": -1.1612846013603848}, {"f": -2, "t": null, "l": -1, "r": -1, "v": -10.433919672396563}, {"f": -2, "t": null, "l": -1, "r": -1, "v": 3.8781909807244936}]}, {"nodes": [{"f": 0, "t": 1.5, "l": 1, "r": 8, "v": -2.5863755581667648e-14}, {"f": 7, "t": 602.4599914550781, "l": 2, "r": 5, "v": 4.902495876899944}, {"f": 6, "t": 559.9450073242188, "l": 3, "r": 4, "v": -9.167150850888305}, {"f": -2, "t": null, "l": -1, "r": -1, "v": 26.352662148579213}, {"f": -2, "t": null, "l": -1, "r": -1, "v": -22.828617389145045}, {"f": 2, "t": 13.5, "l": 6, "r": 7, "v": 14.643020534599499}, {"f": -2, "t": null, "l": -1, "r": -1, "v": 52.43890560246361}, {"f": -2, "t": null, "l": -1, "r": -1, "v": 5.64400028034614}, {"f": 0, "t": 2.5, "l": 9, "r": 12, "v": -3.8519610461357163}, {"f": 5, "t": 218.0, "l": 10, "r": 11, "v": -14.451173029933573}, {"f": -2, "t": null, "l": -1, "r": -1, "v": 6.685367537631616}, {"f": -2, "t": null, "l": -1, "r": -1, "v": -32.56820780213231}, {"f": 9, "t": 670.5464172363281, "l": 13, "r": 14, "v": 5.334022673155759}, {"f": -2, "t": null, "l": -1, "r": -1, "v": -4.075109331304997}, {"f": -2, "t": null, "l": -1, "r": -1, "v": 31.209135685422837}]}, {"nodes": [{"f": 6, "t": 275.5950012207031, "l": 1, "r": 8, "v": -1.7053025658242404e-14}, {"f": 7, "t": 592.5299987792969, "l": 2, "r": 5, "v": -18.01751661166852}, {"f": 4, "t": 3.0, "l": 3, "r": 4, "v": 1.6141341993954181}, {"f": -2, "t": null, "l": -1, "r": -1, "v": -7.866031646558895}, {"f": -2, "t": null, "l": -1, "r": -1, "v": 20.574465891304044}, {"f": 2, "t": 42.5, "l": 6, "r": 7, "v": -47.46499282826443}, {"f": -2, "t": null, "l": -1, "r": -1, "v": -65.67401085836514}, {"f": -2, "t": null, "l": -1, "r": -1, "v": -29.25597479816372}, {"f": 0, "t": 1.5, "l": 9, "r": 12, "v": 0.9482903479825358}, {"f": 7, "t": 602.4599914550781, "l": 10, "r": 11, "v": 6.730252472831654}, {"f": -2, "t": null, "l": -1, "r": -1, "v": -10.522910453305684}, {"f": -2, "t": null, "l": -1, "r": -1, "v": 18.23236109025655}, {"f": 7, "t": 648.8899841308594, "l": 13, "r": 14, "v": -3.2567730155440957}, {"f": -2, "t": null, "l": -1, "r": -1, "v": 6.646414160358846}, {"f": -2, "t": null, "l": -1, "r": -1, "v": -12.80627493516479}]}, {"nodes": [{"f": 7, "t": 837.8499755859375, "l": 1, "r": 8, "v": -2.3305801732931285e-14}, {"f": 8, "t": 747.394287109375, "l": 2, "r": 5, "v": 1.8774211673645615}, {"f": 8, "t": 734.1271362304688, "l": 3, "r": 4, "v": -0.4565169906206188}, {"f": -2, "t": null, "l": -1, "r": -1, "v": 1.1146928813815045}, {"f": -2, "t": null, "l": -1, "r": -1, "v": -55.44886251069494}, {"f": 2, "t": 21.5, "l": 6, "r": 7, "v": 17.15410729235847}, {"f": -2, "t": null, "l": -1, "r": -1, "v": 54.34339293675757}, {"f": -2, "t": null, "l": -1, "r": -1, "v": -4.0969130758695815}, {"f": 7, "t": 978.22998046875, "l": 9, "r": 12, "v": -9.16623275830947}, {"f": 7, "t": 951.7100219726562, "l": 10, "r": 11, "v": -19.54863949160491}, {"f": -2, "t": null, "l": -1, "r": -1, "v": -10.95773415715867}, {"f": -2, "t": null, "l": -1, "r": -1, "v": -49.61680816216675}, {"f": 5, "t": 354.0, "l": 13, "r": 14, "v": 2.5139748166479023}, {"f": -2, "t": null, "l": -1, "r": -1, "v": 7.7805558999291735}, {"f": -2, "t": null, "l": -1, "r": -1, "v": -34.35209276632099}]}, {"nodes": [{"f": 5, "t": 39.0, "l": 1, "r": 2, "v": 1.4210854715202005e-15}, {"f": -2, "t": null, "l": -1, "r": -1, "v": 39.963856506058846}, {"f": 7, "t": 456.510009765625, "l": 3, "r": 6, "v": -0.4036753182430172}, {"f": 2, "t": 46.5, "l": 4, "r": 5, "v": 7.3615828783340795}, {"f": -2, "t": null, "l": -1, "r": -1, "v": 1.0610159323644657}, {"f": -2, "t": null, "l": -1, "r": -1, "v": 47.26517353614164}, {"f": 7, "t": 578.760009765625, "l": 7, "r": 8, "v": -2.622320517265045}, {"f": -2, "t": null, "l": -1, "r": -1, "v": -27.622397194371796}, {"f": -2, "t": null, "l": -1, "r": -1, "v": 1.5443589289194135}]}, {"nodes": [{"f": 2, "t": 45.5, "l": 1, "r": 8, "v": 7.105427357601002e-15}, {"f": 1, "t": 6.5, "l": 2, "r": 5, "v": 1.4682413640053136}, {"f": 6, "t": 835.989990234375, "l": 3, "r": 4, "v": -11.034932645851248}, {"f": -2, "t": null, "l": -1, "r": -1, "v": -7.405098794542152}, {"f": -2, "t": null, "l": -1, "r": -1, "v": -34.628852679360364}, {"f": 1, "t": 15.5, "l": 6, "r": 7, "v": 4.037386708496388}, {"f": -2, "t": null, "l": -1, "r": -1, "v": 17.87942183705037}, {"f": -2, "t": null, "l": -1, "r": -1, "v": -2.742385599366788}, {"f": 7, "t": 337.4199981689453, "l": 9, "r": 12, "v": -10.767103336038907}, {"f": 2, "t": 48.0, "l": 10, "r": 11, "v": 47.29938388661333}, {"f": -2, "t": null, "l": -1, "r": -1, "v": 69.34007408533694}, {"f": -2, "t": null, "l": -1, "r": -1, "v": 25.258693687889718}, {"f": 8, "t": 536.0457153320312, "l": 13, "r": 14, "v": -22.380400780569353}, {"f": -2, "t": null, "l": -1, "r": -1, "v": -8.478814620947}, {"f": -2, "t": null, "l": -1, "r": -1, "v": -54.81743515302151}]}, {"nodes": [{"f": 7, "t": 837.8499755859375, "l": 1, "r": 8, "v": -7.673861546209083e-15}, {"f": 8, "t": 747.394287109375, "l": 2, "r": 5, "v": 1.6923613502600863}, {"f": 8, "t": 734.1271362304688, "l": 3, "r": 4, "v": -0.3983208570136255}, {"f": -2, "t": null, "l": -1, "r": -1, "v": 1.0709324666829758}, {"f": -2, "t": null, "l": -1, "r": -1, "v": -51.82218718639467}, {"f": 9, "t": 737.501953125, "l": 6, "r": 7, "v": 15.376826706960742}, {"f": -2, "t": null, "l": -1, "r": -1, "v": 55.885280379384994}, {"f": -2, "t": null, "l": -1, "r": -1, "v": 0.18615657980164713}, {"f": 6, "t": 1195.1649780273438, "l": 9, "r": 12, "v": -8.26270541597576}, {"f": 6, "t": 1001.4450073242188, "l": 10, "r": 11, "v": -12.990154562682793}, {"f": -2, "t": null, "l": -1, "r": -1, "v": -8.603509169876546}, {"f": -2, "t": null, "l": -1, "r": -1, "v": -39.31002691952028}, {"f": 5, "t": 350.5, "l": 13, "r": 14, "v": 13.798723935323741}, {"f": -2, "t": null, "l": -1, "r": -1, "v": 49.48996369570432}, {"f": -2, "t": null, "l": -1, "r": -1, "v": -4.046895944866549}]}, {"nodes": [{"f": 6, "t": 275.5950012207031, "l": 1, "r": 8, "v": -3.581135388230905e-14}, {"f": 7, "t": 592.5299987792969, "l": 2, "r": 5, "v": -15.916309280328596}, {"f": 8, "t": 511.1464385986328, "l": 3, "r": 4, "v": 1.826439174199436}, {"f": -2, "t": null, "l": -1, "r": -1, "v": 16.404412990425726}, {"f": -2, "t": null, "l": -1, "r": -1, "v": -5.462547733913709}, {"f": 8, "t": 538.6878662109375, "l": 6, "r": 7, "v": -42.530431962120645}, {"f": -2, "t": null, "l": -1, "r": -1, "v": -25.855494283950975}, {"f": -2, "t": null, "l": -1, "r": -1, "v": -59.205369640290314}, {"f": 0, "t": 1.5, "l": 9, "r": 12, "v": 0.8377004884383095}, {"f": 0, "t": 0.5, "l": 10, "r": 11, "v": 6.070635372354547}, {"f": -2, "t": null, "l": -1, "r": -1, "v": -4.947797309840095}, {"f": -2, "t": null, "l": -1, "r": -1, "v": 19.537608650592446}, {"f": 0, "t": 2.5, "l": 13, "r": 14, "v": -2.9680703362280454}, {"f": -2, "t": null, "l": -1, "r": -1, "v": -11.900412874961878}, {"f": -2, "t": null, "l": -1, "r": -1, "v": 5.040236767464356}]}, {"nodes": [{"f": 2, "t": 45.5, "l": 1, "r": 8, "v": -1.8189894035458565e-14}, {"f": 2, "t": 42.5, "l": 2, "r": 5, "v": 1.3107888098381861}, {"f": 1, "t": 17.5, "l": 3, "r": 4, "v": -0.4669913257141243}, {"f": -2, "t": null, "l": -1, "r": -1, "v": 5.787395978243239}, {"f": -2, "t": null, "l": -1, "r": -1, "v": -7.042116440130839}, {"f": 5, "t": 109.0, "l": 6, "r": 7, "v": 19.08859016536129}, {"f": -2, "t": null, "l": -1, "r": -1, "v": 34.77412432282205}, {"f": -2, "t": null, "l": -1, "r": -1, "v": 9.677269670884835}, {"f": 7, "t": 337.4199981689453, "l": 9, "r": 12, "v": -9.61245127214685}, {"f": 3, "t": 11.5, "l": 10, "r": 11, "v": 42.80536105665851}, {"f": -2, "t": null, "l": -1, "r": -1, "v": 63.48901471763111}, {"f": -2, "t": null, "l": -1, "r": -1, "v": 22.121707395685917}, {"f": 8, "t": 536.0457153320312, "l": 13, "r": 14, "v": -20.09601373790792}, {"f": -2, "t": null, "l": -1, "r": -1, "v": -7.445502157629611}, {"f": -2, "t": null, "l": -1, "r": -1, "v": -49.613874091890644}]}, {"nodes": [{"f": 1, "t": 7.5, "l": 1, "r": 8, "v": -1.9895196601282804e-14}, {"f": 5, "t": 224.5, "l": 2, "r": 5, "v": -7.830839677963083}, {"f": 1, "t": 4.5, "l": 3, "r": 4, "v": 3.328702452824944}, {"f": -2, "t": null, "l": -1, "r": -1, "v": -5.399095110178223}, {"f": -2, "t": null, "l": -1, "r": -1, "v": 9.874550625077319}, {"f": 1, "t": 3.5, "l": 6, "r": 7, "v": -14.340572587589433}, {"f": -2, "t": null, "l": -1, "r": -1, "v": -4.017092617176923}, {"f": -2, "t": null, "l": -1, "r": -1, "v": -21.714486852169795}, {"f": 1, "t": 11.5, "l": 9, "r": 12, "v": 1.8368636281641555}, {"f": 0, "t": 0.5, "l": 10, "r": 11, "v": 20.0375465728331}, {"f": -2, "t": null, "l": -1, "r": -1, "v": -24.0231621277983}, {"f": -2, "t": null, "l": -1, "r": -1, "v": 31.052723747990953}, {"f": 5, "t": 200.0, "l": 13, "r": 14, "v": -0.7266128429159779}, {"f": -2, "t": null, "l": -1, "r": -1, "v": -7.084003135892489}, {"f": -2, "t": null, "l": -1, "r": -1, "v": 4.794278727300466}]}, {"nodes": [{"f": 2, "t": 50.5, "l": 1, "r": 8, "v": -2.7853275241795927e-14}, {"f": 9, "t": 536.1626586914062, "l": 2, "r": 5, "v": -0.36066383080930225}, {"f": 1, "t": 17.0, "l": 3, "r": 4, "v": -22.995341810909473}, {"f": -2, "t": null, "l": -1, "r": -1, "v": -9.876373564958271}, {"f": -2, "t": null, "l": -1, "r": -1, "v": -75.47121479471429}, {"f": 2, "t": 7.5, "l": 6, "r": 7, "v": 0.8433084021747494}, {"f": -2, "t": null, "l": -1, "r": -1, "v": 23.029978872967092}, {"f": -2, "t": null, "l": -1, "r": -1, "v": -0.9418260035211862}, {"f": -2, "t": null, "l": -1, "r": -1, "v": 35.705719250118136}]}, {"nodes": [{"f": 0, "t": 1.5, "l": 1, "r": 8, "v": -9.663381206337363e-15}, {"f": 8, "t": 725.1699829101562, "l": 2, "r": 5, "v": 3.950121613722712}, {"f": 7, "t": 653.8250122070312, "l": 3, "r": 4, "v": -0.9206329539406866}, {"f": -2, "t": null, "l": -1, "r": -1, "v": -7.027901631886913}, {"f": -2, "t": null, "l": -1, "r": -1, "v": 13.736811873130259}, {"f": 7, "t": 856.3099975585938, "l": 6, "r": 7, "v": 20.510687143778267}, {"f": -2, "t": null, "l": -1, "r": -1, "v": 51.95551335939922}, {"f": -2, "t": null, "l": -1, "r": -1, "v": -0.45253033330236764}, {"f": 7, "t": 518.5650024414062, "l": 9, "r": 12, "v": -3.1036669822107195}, {"f": 2, "t": 11.0, "l": 10, "r": 11, "v": 9.043505099886655}, {"f": -2, "t": null, "l": -1, "r": -1, "v": -17.6508564428709}, {"f": -2, "t": null, "l": -1, "r": -1, "v": 15.203742378984552}, {"f": 2, "t": 45.5, "l": 13, "r": 14, "v": -7.9625358150496695}, {"f": -2, "t": null, "l": -1, "r": -1, "v": -5.125933380214229}, {"f": -2, "t": null, "l": -1, "r": -1, "v": -33.491957728568636}]}, {"nodes": [{"f": 1, "t": 7.5, "l": 1, "r": 8, "v": 6.8212102632969615e-15}, {"f": 2, "t": 42.5, "l": 2, "r": 5, "v": -7.017512174016317}, {"f": 7, "t": 490.06500244140625, "l": 3, "r": 4, "v": -10.338074823021136}, {"f": -2, "t": null, "l": -1, "r": -1, "v": 2.663173655203053}, {"f": -2, "t": null, "l": -1, "r": -1, "v": -14.671824315762533}, {"f": 5, "t": 120.5, "l": 6, "r": 7, "v": 10.69215528734272}, {"f": -2, "t": null, "l": -1, "r": -1, "v": 1.3367013969406116}, {"f": -2, "t": null, "l": -1, "r": -1, "v": 15.369882232543773}, {"f": 1, "t": 11.5, "l": 9, "r": 12, "v": 1.6460831025470457}, {"f": 0, "t": 0.5, "l": 10, "r": 11, "v": 17.78142761240318}, {"f": -2, "t": null, "l": -1, "r": -1, "v": -21.862108826728516}, {"f": -2, "t": null, "l": -1, "r": -1, "v": 27.692311722186105}, {"f": 1, "t": 12.5, "l": 13, "r": 14, "v": -0.6265006312355085}, {"f": -2, "t": null, "l": -1, "r": -1, "v": -22.90987035350993}, {"f": -2, "t": null, "l": -1, "r": -1, "v": 0.703849799945054}]}, {"nodes": [{"f": 2, "t": 50.5, "l": 1, "r": 8, "v": 0.0}, {"f": 9, "t": 536.1626586914062, "l": 2, "r": 5, "v": -0.3309853788717219}, {"f": 9, "t": 533.6915893554688, "l": 3, "r": 4, "v": -19.081643581532592}, {"f": -2, "t": null, "l": -1, "r": -1, "v": -7.029132443903563}, {"f": -2, "t": null, "l": -1, "r": -1, "v": -67.2916881320487}, {"f": 2, "t": 7.5, "l": 6, "r": 7, "v": 0.6663900574400264}, {"f": -2, "t": null, "l": -1, "r": -1, "v": 20.69228020489}, {"f": -2, "t": null, "l": -1, "r": -1, "v": -0.9448884601708908}, {"f": -2, "t": null, "l": -1, "r": -1, "v": 32.76755250830047}]}, {"nodes": [{"f": 0, "t": 1.5, "l": 1, "r": 8, "v": -2.2737367544323207e-14}, {"f": 8, "t": 725.1699829101562, "l": 2, "r": 5, "v": 3.7950750364082846}, {"f": 7, "t": 653.8250122070312, "l": 3, "r": 4, "v": -0.5814052174927757}, {"f": -2, "t": null, "l": -1, "r": -1, "v": -5.990492348473006}, {"f": -2, "t": null, "l": -1, "r": -1, "v": 12.400403896859777}, {"f": 2, "t": 20.5, "l": 6, "r": 7, "v": 18.67510789967189}, {"f": -2, "t": null, "l": -1, "r": -1, "v": 66.1656114919723}, {"f": -2, "t": null, "l": -1, "r": -1, "v": 6.802482001596786}, {"f": 0, "t": 2.5, "l": 9, "r": 12, "v": -2.981844671463693}, {"f": 6, "t": 617.2250061035156, "l": 10, "r": 11, "v": -10.9593358357253}, {"f": -2, "t": null, "l": -1, "r": -1, "v": 2.9559242247269424}, {"f": -2, "t": null, "l": -1, "r": -1, "v": -27.193805906252916}, {"f": 9, "t": 670.5464172363281, "l": 13, "r": 14, "v": 3.9319810042296996}, {"f": -2, "t": null, "l": -1, "r": -1, "v": -3.750603948677565}, {"f": -2, "t": null, "l": -1, "r": -1, "v": 25.059089624724677}]}, {"nodes": [{"f": 5, "t": 39.0, "l": 1, "r": 2, "v": -2.3305801732931285e-14}, {"f": -2, "t": null, "l": -1, "r": -1, "v": 32.67104508744205}, {"f": 5, "t": 97.5, "l": 3, "r": 6, "v": -0.33001055643883215}, {"f": 7, "t": 647.875, "l": 4, "r": 5, "v": -8.65180974965001}, {"f": -2, "t": null, "l": -1, "r": -1, "v": -17.786050668248333}, {"f": -2, "t": null, "l": -1, "r": -1, "v": 9.616672087546636}, {"f": 5, "t": 113.5, "l": 7, "r": 8, "v": 1.1560250137774497}, {"f": -2, "t": null, "l": -1, "r": -1, "v": 25.7089167335882}, {"f": -2, "t": null, "l": -1, "r": -1, "v": -0.7326589646695313}]}, {"nodes": [{"f": 7, "t": 665.739990234375, "l": 1, "r": 8, "v": -7.389644451905042e-15}, {"f": 7, "t": 656.385009765625, "l": 2, "r": 5, "v": 2.8206703672367497}, {"f": 5, "t": 258.5, "l": 3, "r": 4, "v": 0.7564072975449554}, {"f": -2, "t": null, "l": -1, "r": -1, "v": -3.435260046093992}, {"f": -2, "t": null, "l": -1, "r": -1, "v": 13.331409328461799}, {"f": 8, "t": 574.1771545410156, "l": 6, "r": 7, "v": 60.62003631860699}, {"f": -2, "t": null, "l": -1, "r": -1, "v": 62.116280042482344}, {"f": -2, "t": null, "l": -1, "r": -1, "v": 59.12379259473164}, {"f": 7, "t": 704.4649963378906, "l": 9, "r": 12, "v": -3.895211459517434}, {"f": 8, "t": 705.2435913085938, "l": 10, "r": 11, "v": -19.053506769275835}, {"f": -2, "t": null, "l": -1, "r": -1, "v": -8.407117534532006}, {"f": -2, "t": null, "l": -1, "r": -1, "v": -43.895081650344764}, {"f": 7, "t": 751.0, "l": 13, "r": 14, "v": 0.8417558247820658}, {"f": -2, "t": null, "l": -1, "r": -1, "v": 34.69067609607646}, {"f": -2, "t": null, "l": -1, "r": -1, "v": -2.6598566170759748}]}, {"nodes": [{"f": 2, "t": 50.5, "l": 1, "r": 8, "v": 9.947598300641402e-15}, {"f": 9, "t": 539.9496459960938, "l": 2, "r": 5, "v": -0.3081478625595257}, {"f": 6, "t": 597.3450012207031, "l": 3, "r": 4, "v": -12.172780814758141}, {"f": -2, "t": null, "l": -1, "r": -1, "v": -2.605278533779881}, {"f": -2, "t": null, "l": -1, "r": -1, "v": -31.307785376714662}, {"f": 2, "t": 7.5, "l": 6, "r": 7, "v": 0.8783154326603358}, {"f": -2, "t": null, "l": -1, "r": -1, "v": 51.56153719283012}, {"f": -2, "t": null, "l": -1, "r": -1, "v": -0.8693818694144845}, {"f": -2, "t": null, "l": -1, "r": -1, "v": 30.50663839339404}]}, {"nodes": [{"f": 1, "t": 25.5, "l": 1, "r": 8, "v": 1.0516032489249483e-14}, {"f": 1, "t": 24.5, "l": 2, "r": 5, "v": 1.345547102147052}, {"f": 5, "t": 64.0, "l": 3, "r": 4, "v": -0.06485276009769056}, {"f": -2, "t": null, "l": -1, "r": -1, "v": 16.477300836519237}, {"f": -2, "t": null, "l": -1, "r": -1, "v": -1.3882250478270448}, {"f": 5, "t": 305.0, "l": 6, "r": 7, "v": 39.4263433827551}, {"f": -2, "t": null, "l": -1, "r": -1, "v": 58.936182983229685}, {"f": -2, "t": null, "l": -1, "r": -1, "v": 0.40666418180592245}, {"f": 7, "t": 475.25, "l": 9, "r": 12, "v": -7.064122286271957}, {"f": 1, "t": 29.5, "l": 10, "r": 11, "v": 7.551554807517832}, {"f": -2, "t": null, "l": -1, "r": -1, "v": 12.240445518785748}, {"f": -2, "t": null, "l": -1, "r": -1, "v": -6.515117326285917}, {"f": 7, "t": 640.5449829101562, "l": 13, "r": 14, "v": -11.936014650868552}, {"f": -2, "t": null, "l": -1, "r": -1, "v": -28.784210855918616}, {"f": -2, "t": null, "l": -1, "r": -1, "v": -3.511916548343521}]}, {"nodes": [{"f": 5, "t": 356.5, "l": 1, "r": 8, "v": 2.5863755581667648e-14}, {"f": 9, "t": 834.8076782226562, "l": 2, "r": 5, "v": 0.303185644710027}, {"f": 6, "t": 736.2349853515625, "l": 3, "r": 4, "v": -0.2480984488419505}, {"f": -2, "t": null, "l": -1, "r": -1, "v": 2.167451920726642}, {"f": -2, "t": null, "l": -1, "r": -1, "v": -5.390883106633148}, {"f": 0, "t": 2.0, "l": 6, "r": 7, "v": 27.04046418198095}, {"f": -2, "t": null, "l": -1, "r": -1, "v": 42.86029378180183}, {"f": -2, "t": null, "l": -1, "r": -1, "v": 11.220634582160073}, {"f": -2, "t": null, "l": -1, "r": -1, "v": -30.01537882629009}]}, {"nodes": [{"f": 6, "t": 275.5950012207031, "l": 1, "r": 8, "v": 4.5190517994342374e-14}, {"f": 6, "t": 230.30500030517578, "l": 2, "r": 5, "v": -13.269209343213765}, {"f": 5, "t": 199.5, "l": 3, "r": 4, "v": 8.347206199332788}, {"f": -2, "t": null, "l": -1, "r": -1, "v": 14.095408102460851}, {"f": -2, "t": null, "l": -1, "r": -1, "v": 2.5990042962047255}, {"f": 5, "t": 101.5, "l": 6, "r": 7, "v": -27.6801530382448}, {"f": -2, "t": null, "l": -1, "r": -1, "v": -48.32094828316258}, {"f": -2, "t": null, "l": -1, "r": -1, "v": -17.359755415785912}, {"f": 0, "t": 1.5, "l": 9, "r": 12, "v": 0.6983794391165615}, {"f": 7, "t": 578.760009765625, "l": 10, "r": 11, "v": 4.624740579746279}, {"f": -2, "t": null, "l": -1, "r": -1, "v": -10.747184177184364}, {"f": -2, "t": null, "l": -1, "r": -1, "v": 10.45547065996135}, {"f": 7, "t": 648.8899841308594, "l": 13, "r": 14, "v": -2.157155935886869}, {"f": -2, "t": null, "l": -1, "r": -1, "v": 4.794862784188347}, {"f": -2, "t": null, "l": -1, "r": -1, "v": -8.860888273102256}]}]}, "history": {"y": [760.35, 318.27, 658.2, 668.65, 532.81, 580.86, 617.63, 787.64, 618.86, 562.69, 251.74, 418.48, 607.06, 580.63, 621.66, 215.88, 689.46, 391.61, 726.92, 756.45, 339.12, 668.04, 615.59, 588.94, 649.45, 244.73, 597.86, 557.2, 335.72, 606.69, 760.47, 454.39, 327.3, 588.86, 567.43, 458.63, 583.79, 699.64, 261.89, 610.9, 473.59, 663.44, 631.13, 311.75, 289.3, 683.05, 822.16, 801.52, 643.54, 506.54, 654.24, 697.4, 998.8, 950.77, 576.89, 620.91, 654.57, 669.68, 794.38, 356.35, 1025.67, 792.75, 489.56, 709.29, 853.54, 357.12, 876.27, 365.42, 902.66, 678.71, 952.65, 346.06, 813.54, 786.31, 610.52, 202.58, 745.55, 644.59, 957.66, 1491.47, 573.27, 1565.41, 1050.24, 673.66, 902.66, 760.88, 304.22, 911.1, 784.03, 394.15, 1180.84, 1181.73, 393.3, 931.4, 1208.6, 1446.56, 863.19, 1239.02, 385.71, 724.57, 819.65, 295.4, 1005.59, 1321.26, 1166.16, 1530.6, 428.48, 966.78, 912.81, 930.47, 510.17, 868.57, 884.16, 864.23, 868.77, 2277.07, 2399.15, 847.93, 912.48, 1113.26, 1072.64, 326.28, 924.43, 933.94, 622.55], "trend0": "2024-08-15"}, "weekday_stats": {"0": {"avg_headcount": 18.923076923076923, "avg_price_pp": 14.304615384615385}, "1": {"avg_headcount": 38.96666666666667, "avg_price_pp": 14.988666666666667}, "2": {"avg_headcount": 40.51428571428571, "avg_price_pp": 14.790857142857142}, "3": {"avg_headcount": 41.89473684210526, "avg_price_pp": 14.861842105263158}, "4": {"avg_headcount": 30.0, "avg_price_pp": 15.375}}}